Workbook
Name descriptions: DishDescriptions!$A$1:$K$591
Name Groups: RecipeNotes!$A$2:$A$36
Name recipe_notes: DishNotes!$A$1:$N$573

Sheet DishNotes
A1: dish_name | B1: dish_pk | C1: mltext_pk | D1: Type | E1: New guide | F1: Group | G1: New proposal | H1: New proposal | I1: en | J1: da | K1: de | L1: lv | M1: et
A2: Pickling | B2: 141 | C2: 1741 | D2: =VLOOKUP(B2,[1]ManipulationPage!$A$3:$D$541,4,FALSE) -> 0 | I2: Your vegetables will already gain a sour flavor within 30 minutes, but they gain more flavor the longer you keep them. Consume within 2 weeks. | J2: Your vegetables will already gain a sour flavor within 30 minutes, but they gain more flavor the longer you keep them. Consume within 2 weeks. | K2: Your vegetables will already gain a sour flavor within 30 minutes, but they gain more flavor the longer you keep them. Consume within 2 weeks.
A3: Asian Marinade | B3: 1094 | C3: 9263 | D3: =VLOOKUP(B3,[1]ManipulationPage!$A$3:$D$541,4,FALSE) -> Asia | F3: Marinade | G3: =VLOOKUP($F3,RecipeNotes!$A$2:$E$62,3,FALSE) -> Shortcut recipe: Mix ingredients and stir around with a fork. | H3: =VLOOKUP($F3,RecipeNotes!$A$2:$E$62,5,FALSE) -> Shortcut opskrift: Bland ingredienser og rør rundt med en gaffel. | I3: The longer you let your ingredients marinate, the deeper their flavor will be. | J3: Jo længere du lader dine ingredienser marinere, jo dybere vil deres smag være. | K3: Je länger du deine Zutaten marinieren lässt, desto intensiver wird ihr Geschmack.
A4: Asian Marinade | B4: 101 | C4: 1479 | D4: =VLOOKUP(B4,[1]ManipulationPage!$A$3:$D$541,4,FALSE) -> Asia | F4: Marinade | G4: =VLOOKUP($F4,RecipeNotes!$A$2:$E$62,3,FALSE) -> Shortcut recipe: Mix ingredients and stir around with a fork. | H4: =VLOOKUP($F4,RecipeNotes!$A$2:$E$62,5,FALSE) -> Shortcut opskrift: Bland ingredienser og rør rundt med en gaffel. | I4: The longer you let your ingredients marinate, the deeper their flavor will be. | J4: Jo længere du lader dine ingredienser marinere, jo dybere vil deres smag være. | K4: Je länger du deine Zutaten marinieren lässt, desto intensiver wird ihr Geschmack.
A5: Asian Salad | B5: 988 | C5: 5420 | D5: =VLOOKUP(B5,[1]ManipulationPage!$A$3:$D$541,4,FALSE) -> Asia | E5: ! | F5: =RecipeNotes!A5 -> Salad | G5: =VLOOKUP($F5,RecipeNotes!$A$2:$E$62,3,FALSE) -> Shortcut recipe: Cut and mix all ingredients. Taste and balance with salt, sugar, sour, and umami. | H5: =VLOOKUP($F5,RecipeNotes!$A$2:$E$62,5,FALSE) -> Shortcut opskrift: Skær og bland alle ingredienser. Smag til med salt, sukker, syre og umami. | I5: =RecipeNotes!B2 -> Fry your onions and spices with a bit of oil. Add your condiments. Add veggies to the pan. Cook your other ingredients on the side. Once all your ingredients are cooked and ready to eat, mix them. Before toppings, taste and balance your dish by adding salt, sugar, sour, or umami ingredients for increased flavor. Too sour? Add salt and sugar. Too spicy? Add oil and sugar. Too Salty? Add bitter ingredients or fresh herbs. Add toppings and enjoy! | J5: A delicious dressing is just as important as the tasty vegetables! | K5: Ein leckeres Dressing ist genauso wichtig wie das leckere Gemüse! | L5: Garšīga mērce ir tikpat svarīga, kā garšīgi dārzeņi. | M5: Hõrk kaste on sama oluline kui maitsvad köögiviljad!
A6: Chow Mein | B6: 3 | C6: 977 | D6: =VLOOKUP(B6,[1]ManipulationPage!$A$3:$D$541,4,FALSE) -> Asia | E6: ! | F6: Stir-Fry | G6: =VLOOKUP($F6,RecipeNotes!$A$2:$E$62,3,FALSE) -> Shortcut recipe: Fry onions and spices on a pan. Add veggies. Taste and balance with salt, sugar, sour, and umami. | H6: =VLOOKUP($F6,RecipeNotes!$A$2:$E$62,5,FALSE) -> Shortcut opskrift: Steg løg og krydderier på panden. Tilføj grøntsager Smag til med salt, sukker, syre og umami. | I6: The trick to the perfect Chow Mein is to cook the noodles until they are al dente and then rinse them with cold water to stop the cooking process. | J6: Tricket bag en perfekt Chow Mein er at koge nudlerne al dente, og så vaske dem i koldt vand, så kogeprocessen stopper brat | K6: Der Trick hinter dem perfekten Chow Mein ist, die Nudeln al dente zu kochen und sie dann mit kaltem Wasser abzuschrecken, um den Kochvorgang abrupt zu beenden.
A7: Congee | B7: 361 | D7: =VLOOKUP(B7,[1]ManipulationPage!$A$3:$D$541,4,FALSE) -> Asia | E7: ! | F7: Congee | G7: =VLOOKUP($F7,RecipeNotes!$A$2:$E$62,3,FALSE) -> Shortcut recipe: Fry onions and spices on a pan. Add rice and boiling water with stock, let simmer. Taste and balance with salt, sugar, sour, and umami. | H7: =VLOOKUP($F7,RecipeNotes!$A$2:$E$62,5,FALSE) -> Shortcut opskrift: Steg løg og krydderier på panden. Tilføj ris og kogt vand med buillon og lad simre. Smag til med salt, sukker, syre og umami.
A8: Japanese Omelette | B8: 31 | C8: 1135 | D8: =VLOOKUP(B8,[1]ManipulationPage!$A$3:$D$541,4,FALSE) -> Asia | E8: ! | F8: Omelette | G8: =VLOOKUP($F8,RecipeNotes!$A$2:$E$62,3,FALSE) -> Shortcut recipe: Fry onions and spices on a pan. Whisk eggs well with salt, then add to pan. Omelette is done when egg isn't runny. | H8: =VLOOKUP($F8,RecipeNotes!$A$2:$E$62,5,FALSE) -> Shortcut opskrift: Steg løg og krydderier på panden. Bland æg grundigt med salt og andre smags-ingredienser. Tilføj så til panden. Omeletten er klar, når ægget ikke løber længere. | I8: If you can crack an egg, then you can make an omelette! | J8: Hvis du slår et æg ud kan du lave en omelet! | K8: Wenn du ein Ei aufschlagen kannst, dann kannst du auch ein Omelette machen!
A9: Japanese Pasta | B9: 930 | D9: =VLOOKUP(B9,[1]ManipulationPage!$A$3:$D$541,4,FALSE) -> Asia | E9: ! | F9: Pasta | G9: =VLOOKUP($F9,RecipeNotes!$A$2:$E$62,3,FALSE) -> Shortcut recipe: Fry onions and spices on a pan. Mix with cooked pasta, including a cup of the pasta water (for creamy consistency). | H9: =VLOOKUP($F9,RecipeNotes!$A$2:$E$62,5,FALSE) -> Shortcut opskrift: Steg løg og krydderier på panden. Ibland den kogte pasta med en kop pasta vand.
A10: Kimchi Sandwich | B10: 552 | D10: =VLOOKUP(B10,[1]ManipulationPage!$A$3:$D$541,4,FALSE) -> Asia | F10: Sandwich | G10: =VLOOKUP($F10,RecipeNotes!$A$2:$E$62,3,FALSE) -> Shortcut recipe: Prepare your ingredients seperately and add as layers on the bread. | H10: =VLOOKUP($F10,RecipeNotes!$A$2:$E$62,5,FALSE) -> Shortcut opskrift: Forbered dine ingredienser sperat og put på brøddet i lag.
A11: Korean Kimchi Stew | B11: 1012 | C11: 5856 | D11: =VLOOKUP(B11,[1]ManipulationPage!$A$3:$D$541,4,FALSE) -> Asia | F11: Stew | G11: =VLOOKUP($F11,RecipeNotes!$A$2:$E$62,3,FALSE) -> Shortcut recipe: Fry onions and spices on a pan. Add veggies. Add water with stock/broth. Taste and balance with salt, sugar, sour, and umami. | H11: =VLOOKUP($F11,RecipeNotes!$A$2:$E$62,5,FALSE) -> Shortcut opskrift: Steg løg og krydderier på panden. Tilføj grøntsager Til føj vand med buillon. Smag til med salt, sukker, syre og umami. | I11: Stews gain even more flavor when kept in the fridge overnight so don't worry if you can't finish it all. | J11: Gryderetten får mere smag, når den opbevares i køleskabet natten over, så bare rolig hvis du ikke kan færdiggøre det hele. | K11: Eintöpfe schmecken noch intensiver, wenn sie über Nacht im Kühlschrank aufbewahrt wurden. Also keine Sorge, wenn du nicht alles auf einmal essen kannst! | L11: Sautējumi ir garšīgāki, ja tos pa nakti atstāj ledusskapī, tāpēc nesatraucieties, ja neapēdat to vienā dienā. | M11: Hautised saavad maitset veelgi juurde, kui neid üleöö külmkapis hoida, seega ära muretse, kui sa ei jõua kõike korraga ära süüa.
A12: Korean Pasta | B12: 931 | D12: =VLOOKUP(B12,[1]ManipulationPage!$A$3:$D$541,4,FALSE) -> Asia | E12: ! | F12: Pasta | G12: =VLOOKUP($F12,RecipeNotes!$A$2:$E$62,3,FALSE) -> Shortcut recipe: Fry onions and spices on a pan. Mix with cooked pasta, including a cup of the pasta water (for creamy consistency). | H12: =VLOOKUP($F12,RecipeNotes!$A$2:$E$62,5,FALSE) -> Shortcut opskrift: Steg løg og krydderier på panden. Ibland den kogte pasta med en kop pasta vand.
A13: Korean Style Pizza | B13: 61 | C13: 1289 | D13: =VLOOKUP(B13,[1]ManipulationPage!$A$3:$D$541,4,FALSE) -> Asia | E13: ! | F13: Pizza | G13: =VLOOKUP($F13,RecipeNotes!$A$2:$E$62,3,FALSE) -> Shortcut recipe: Make your suco of fried onions, spices, and your choice of paste. Add to pizza with your choice of veggies. | H13: =VLOOKUP($F13,RecipeNotes!$A$2:$E$62,5,FALSE) -> Shortcut opskrift: Smør din pizza sauce i tyndt lag (lavet af løg, krydderier og din sauce stegt på en pande). Tilføj dine grøntsager på toppen. | I13: - | J13: - | K13: -
A14: Miso Soup | B14: 56 | C14: 1259 | D14: =VLOOKUP(B14,[1]ManipulationPage!$A$3:$D$541,4,FALSE) -> Asia | E14: ! | F14: =RecipeNotes!A10 -> Chunky soup | G14: =VLOOKUP($F14,RecipeNotes!$A$2:$E$62,3,FALSE) -> Shortcut recipe: Fry onions and spices on a pan. Add veggies. Add water with stock/broth. Taste and balance with salt, sugar, sour, and umami. | H14: =VLOOKUP($F14,RecipeNotes!$A$2:$E$62,5,FALSE) -> Shortcut opskrift: Steg løg og krydderier på panden. Tilføj grøntsager Til føj vand med buillon. Smag til med salt, sukker, syre og umami. | I14: Miso is responsible for the deep umami flavor of this soup, don't shy away from adding more. | J14: Miso er det, som giver den dybe umamismag til suppen, så ikke vær bange for at tilføje mere! | K14: Miso ist verantwortlich für das intensive Umami-Aroma dieser Suppe. Gib ruhig nach deinem Geschmack mehr dazu!
A15: Pad Thai | B15: 258 | C15: 2422 | D15: =VLOOKUP(B15,[1]ManipulationPage!$A$3:$D$541,4,FALSE) -> Asia | E15: ! | F15: =RecipeNotes!A2 -> Stir-Fry | G15: =VLOOKUP($F15,RecipeNotes!$A$2:$E$62,3,FALSE) -> Shortcut recipe: Fry onions and spices on a pan. Add veggies. Taste and balance with salt, sugar, sour, and umami. | H15: =VLOOKUP($F15,RecipeNotes!$A$2:$E$62,5,FALSE) -> Shortcut opskrift: Steg løg og krydderier på panden. Tilføj grøntsager Smag til med salt, sukker, syre og umami. | I15: Cook on high heat to make your dish ready quicker! | J15: Kog panden på højeste volumen, så bliver retten færdig hurtigere. | K15: Arbeite mit sehr hoher Temperatur, damit dein Gericht schneller fertig ist!
A16: Ramen | B16: 1059 | C16: 7733 | D16: =VLOOKUP(B16,[1]ManipulationPage!$A$3:$D$541,4,FALSE) -> Asia | E16: ! | F16: =F14 -> Chunky soup | G16: =VLOOKUP($F16,RecipeNotes!$A$2:$E$62,3,FALSE) -> Shortcut recipe: Fry onions and spices on a pan. Add veggies. Add water with stock/broth. Taste and balance with salt, sugar, sour, and umami. | H16: =VLOOKUP($F16,RecipeNotes!$A$2:$E$62,5,FALSE) -> Shortcut opskrift: Steg løg og krydderier på panden. Tilføj grøntsager Til føj vand med buillon. Smag til med salt, sukker, syre og umami.
A17: Sichuan Roasted Veggies | B17: 317 | C17: 2714 | D17: =VLOOKUP(B17,[1]ManipulationPage!$A$3:$D$541,4,FALSE) -> Asia | E17: ! | F17: =RecipeNotes!A12 -> Oven roast | G17: =VLOOKUP($F17,RecipeNotes!$A$2:$E$62,3,FALSE) -> Shortcut recipe: Roast veggies with onion, spices, salt, and oil in the oven. Taste and balance with salt, sugar, sour, and umami. | H17: =VLOOKUP($F17,RecipeNotes!$A$2:$E$62,5,FALSE) -> Shortcut opskrift: Læg grøntsagerne i ovnen med løg, krydderier, salt og olie. Smag til med salt, sukker, syre og umami. | I17: Roasting your veggies gives them a deeper aromatic profile. Enjoy :) | J17: Roasting your veggies gives them a deeper aromatic profile. Enjoy :) | K17: Roasting your veggies gives them a deeper aromatic profile. Enjoy :)
A18: Sichuan Stir-Fry | B18: 967 | C18: 5060 | D18: =VLOOKUP(B18,[1]ManipulationPage!$A$3:$D$541,4,FALSE) -> Asia | E18: ! | F18: Stir-Fry | G18: =VLOOKUP($F18,RecipeNotes!$A$2:$E$62,3,FALSE) -> Shortcut recipe: Fry onions and spices on a pan. Add veggies. Taste and balance with salt, sugar, sour, and umami. | H18: =VLOOKUP($F18,RecipeNotes!$A$2:$E$62,5,FALSE) -> Shortcut opskrift: Steg løg og krydderier på panden. Tilføj grøntsager Smag til med salt, sukker, syre og umami. | I18: Cook on high heat to make your dish ready quicker! | J18: Kog panden på højeste volumen, så bliver retten færdig hurtigere. | K18: Arbeite mit sehr hoher Temperatur, damit dein Gericht schneller fertig ist! | L18: Lai ēdiena pagatavošana būtu ātrāka, gatavojiet augstākā temperatūrā. | M18: Kuumuta kõrgel kuumusel, et sinu roog kiiremini valmiks!
A19: Tofu Stir-Fry | B19: 969 | C19: 5088 | D19: =VLOOKUP(B19,[1]ManipulationPage!$A$3:$D$541,4,FALSE) -> Asia | E19: ! | F19: Stir-Fry | G19: =VLOOKUP($F19,RecipeNotes!$A$2:$E$62,3,FALSE) -> Shortcut recipe: Fry onions and spices on a pan. Add veggies. Taste and balance with salt, sugar, sour, and umami. | H19: =VLOOKUP($F19,RecipeNotes!$A$2:$E$62,5,FALSE) -> Shortcut opskrift: Steg løg og krydderier på panden. Tilføj grøntsager Smag til med salt, sukker, syre og umami. | I19: Cook on high heat to make your dish ready quicker! | J19: Kog panden på højeste volumen, så bliver retten færdig hurtigere. | K19: Arbeite mit sehr hoher Temperatur, damit dein Gericht schneller fertig ist! | L19: Lai ēdiena pagatavošana būtu ātrāka, gatavojiet to uz lielākas uguns. | M19: Kuumuta kõrgel kuumusel, et sinu roog kiiremini valmiks!
A20: Banana Protein Bites | B20: 389 | C20: 2928 | D20: =VLOOKUP(B20,[1]ManipulationPage!$A$3:$D$541,4,FALSE) -> Baking | F20: Energy Balls | G20: =VLOOKUP($F20,RecipeNotes!$A$2:$E$62,3,FALSE) -> Shortcut recipe: Mash until reaches a cookie dough-like consistency. Add a little more wet or dry ingredients if needed to get the right texture. Form into balls and enjoy! | H20: =VLOOKUP($F20,RecipeNotes!$A$2:$E$62,5,FALSE) -> Shortcut opskrift: Ælt indtil konsistensen minder om kagedej. Form indtil kugler. | I20: Simply put all the ingredients into a food processor and you're ready to roll your own energy balls. | J20: Læg blot alle dine valgte ingredienserne i en madprocessor, og så er du klar til at rulle dine egne energikugler. | K20: Simply put all the ingredients into a food processor and you're ready to roll your own energy balls.
A21: Banana slices | B21: 777 | C21: 3726 | D21: =VLOOKUP(B21,[1]ManipulationPage!$A$3:$D$541,4,FALSE) -> Baking | G21: =VLOOKUP($F21,RecipeNotes!$A$2:$E$62,3,FALSE) -> #N/A | H21: =VLOOKUP($F21,RecipeNotes!$A$2:$E$62,5,FALSE) -> #N/A
A22: Beetroot Choco Cake | B22: 447 | C22: 3066 | D22: =VLOOKUP(B22,[1]ManipulationPage!$A$3:$D$541,4,FALSE) -> Baking | F22: Cake | G22: =VLOOKUP($F22,RecipeNotes!$A$2:$E$62,3,FALSE) -> Shortcut recipe: Fold the dry ingredients gently into the wet ingredients. Bake at 180°C until a toothpick inserted in the middle comes out clean (about 40 minutes). | H22: =VLOOKUP($F22,RecipeNotes!$A$2:$E$62,5,FALSE) -> Shortcut opskrift: Fold de tørre ingredienser ind i de våde. Bag i ovnen indtil en tandstik kan komme ud af dem uden dej sidder fast (ca 40 minutter). | I22: Vegetables can indeed be used in cake! | J22: Grøntsager kan sagtens bruges i kage! | K22: Vegetables can indeed be used in cake!
A23: Berry Almond Brownie | B23: 627 | C23: 3389 | D23: =VLOOKUP(B23,[1]ManipulationPage!$A$3:$D$541,4,FALSE) -> Baking | F23: Cake | G23: =VLOOKUP($F23,RecipeNotes!$A$2:$E$62,3,FALSE) -> Shortcut recipe: Fold the dry ingredients gently into the wet ingredients. Bake at 180°C until a toothpick inserted in the middle comes out clean (about 40 minutes). | H23: =VLOOKUP($F23,RecipeNotes!$A$2:$E$62,5,FALSE) -> Shortcut opskrift: Fold de tørre ingredienser ind i de våde. Bag i ovnen indtil en tandstik kan komme ud af dem uden dej sidder fast (ca 40 minutter).
A24: Berry Almond Brownies | B24: 628 | C24: 3391 | D24: =VLOOKUP(B24,[1]ManipulationPage!$A$3:$D$541,4,FALSE) -> Baking | F24: Cake | G24: =VLOOKUP($F24,RecipeNotes!$A$2:$E$62,3,FALSE) -> Shortcut recipe: Fold the dry ingredients gently into the wet ingredients. Bake at 180°C until a toothpick inserted in the middle comes out clean (about 40 minutes). | H24: =VLOOKUP($F24,RecipeNotes!$A$2:$E$62,5,FALSE) -> Shortcut opskrift: Fold de tørre ingredienser ind i de våde. Bag i ovnen indtil en tandstik kan komme ud af dem uden dej sidder fast (ca 40 minutter).
A25: Berry Muffins | B25: 467 | C25: 3100 | D25: =VLOOKUP(B25,[1]ManipulationPage!$A$3:$D$541,4,FALSE) -> Baking | F25: Sweet muffin | G25: =VLOOKUP($F25,RecipeNotes!$A$2:$E$62,3,FALSE) -> Shortcut recipe: Gently mix the wet ingredients into the dry. Bake in oven until a toothpick comes out clean when pricking them (about 30 minutes) | H25: =VLOOKUP($F25,RecipeNotes!$A$2:$E$62,5,FALSE) -> Shortcut opskrift: Ælt de våde ingredienser indi i de tørre nænsomt. Bag i ovnen indtil en tandstik kan komme ud af dem uden dej sidder fast.
A26: Black Bean Brownies | B26: 457 | C26: 3081 | D26: =VLOOKUP(B26,[1]ManipulationPage!$A$3:$D$541,4,FALSE) -> Baking | F26: Cake | G26: =VLOOKUP($F26,RecipeNotes!$A$2:$E$62,3,FALSE) -> Shortcut recipe: Fold the dry ingredients gently into the wet ingredients. Bake at 180°C until a toothpick inserted in the middle comes out clean (about 40 minutes). | H26: =VLOOKUP($F26,RecipeNotes!$A$2:$E$62,5,FALSE) -> Shortcut opskrift: Fold de tørre ingredienser ind i de våde. Bag i ovnen indtil en tandstik kan komme ud af dem uden dej sidder fast (ca 40 minutter). | I26: Black beans provide softness and body to these brownies - and don't worry, the chocolate taste hides the bean flavor. | J26: Sorte bønner giver brownien blødhed og struktur - og bare rolig, chokoladen skjuler bønensmag. | K26: Black beans provide softness and body to these brownies - and don't worry, the chocolate taste hides the bean flavor.
A27: Bread Buns | B27: 1149 | C27: 10081 | D27: =VLOOKUP(B27,[1]ManipulationPage!$A$3:$D$541,4,FALSE) -> Baking | F27: Bread | G27: =VLOOKUP($F27,RecipeNotes!$A$2:$E$62,3,FALSE) -> Shortcut recipe: knead in the wet ingredients into the dry until no flour pockets remain. Raise for 5 hours and bake for 1 hour (180 degrees). | H27: =VLOOKUP($F27,RecipeNotes!$A$2:$E$62,5,FALSE) -> Shortcut opskrift: Ælt de våde ingredienser indi ide tørre, indtil der ikke er mel-lommer. Hæv i mindst 5 timer, bag i ovnen i en time (180 grader).
A28: Bread Pudding Dessert | B28: 421 | C28: 3012 | D28: =VLOOKUP(B28,[1]ManipulationPage!$A$3:$D$541,4,FALSE) -> Baking | G28: =VLOOKUP($F28,RecipeNotes!$A$2:$E$62,3,FALSE) -> #N/A | H28: =VLOOKUP($F28,RecipeNotes!$A$2:$E$62,5,FALSE) -> #N/A | I28: Experiment with different bread types for various flavors.
A29: Breakfast Buns | B29: 481 | C29: 3126 | D29: =VLOOKUP(B29,[1]ManipulationPage!$A$3:$D$541,4,FALSE) -> Baking | F29: Bread | G29: =VLOOKUP($F29,RecipeNotes!$A$2:$E$62,3,FALSE) -> Shortcut recipe: knead in the wet ingredients into the dry until no flour pockets remain. Raise for 5 hours and bake for 1 hour (180 degrees). | H29: =VLOOKUP($F29,RecipeNotes!$A$2:$E$62,5,FALSE) -> Shortcut opskrift: Ælt de våde ingredienser indi ide tørre, indtil der ikke er mel-lommer. Hæv i mindst 5 timer, bag i ovnen i en time (180 grader).
A30: Buchteln | B30: 743 | C30: 3658 | D30: =VLOOKUP(B30,[1]ManipulationPage!$A$3:$D$541,4,FALSE) -> Baking | F30: Cake | G30: =VLOOKUP($F30,RecipeNotes!$A$2:$E$62,3,FALSE) -> Shortcut recipe: Fold the dry ingredients gently into the wet ingredients. Bake at 180°C until a toothpick inserted in the middle comes out clean (about 40 minutes). | H30: =VLOOKUP($F30,RecipeNotes!$A$2:$E$62,5,FALSE) -> Shortcut opskrift: Fold de tørre ingredienser ind i de våde. Bag i ovnen indtil en tandstik kan komme ud af dem uden dej sidder fast (ca 40 minutter).
A31: Bundt Cake | B31: 1153 | C31: 10097 | D31: =VLOOKUP(B31,[1]ManipulationPage!$A$3:$D$541,4,FALSE) -> Baking | F31: Cake | G31: =VLOOKUP($F31,RecipeNotes!$A$2:$E$62,3,FALSE) -> Shortcut recipe: Fold the dry ingredients gently into the wet ingredients. Bake at 180°C until a toothpick inserted in the middle comes out clean (about 40 minutes). | H31: =VLOOKUP($F31,RecipeNotes!$A$2:$E$62,5,FALSE) -> Shortcut opskrift: Fold de tørre ingredienser ind i de våde. Bag i ovnen indtil en tandstik kan komme ud af dem uden dej sidder fast (ca 40 minutter).
A32: Chia Pudding | B32: 667 | C32: 3487 | D32: =VLOOKUP(B32,[1]ManipulationPage!$A$3:$D$541,4,FALSE) -> Baking | G32: =VLOOKUP($F32,RecipeNotes!$A$2:$E$62,3,FALSE) -> #N/A | H32: =VLOOKUP($F32,RecipeNotes!$A$2:$E$62,5,FALSE) -> #N/A | I32: Chia seeds will thicken your porridge, so don't worry if it looks too runny at first. | J32: Chia frø samler vand og bliver tykkere... så bare rolig, hvis den virker for løbende i starten. | K32: Chia verdickt deinen Brei, mache dir also keine Sorgen, wenn er zu Beginn zu flüssig aussieht.
A33: Choco Berry Muffins | B33: 826 | C33: 3830 | D33: =VLOOKUP(B33,[1]ManipulationPage!$A$3:$D$541,4,FALSE) -> Baking | F33: Sweet muffin | G33: =VLOOKUP($F33,RecipeNotes!$A$2:$E$62,3,FALSE) -> Shortcut recipe: Gently mix the wet ingredients into the dry. Bake in oven until a toothpick comes out clean when pricking them (about 30 minutes) | H33: =VLOOKUP($F33,RecipeNotes!$A$2:$E$62,5,FALSE) -> Shortcut opskrift: Ælt de våde ingredienser indi i de tørre nænsomt. Bag i ovnen indtil en tandstik kan komme ud af dem uden dej sidder fast. | I33: Soft and tender muffins can be made to fit for almost any occasion! Breakfast, snack, dessert, dinner...you name it! | J33: Soft and tender muffins can be made to fit for almost any occasion! Breakfast, snack, dessert, dinner...you name it! | K33: Soft and tender muffins can be made to fit for almost any occasion! Breakfast, snack, dessert, dinner...you name it!
A34: Chocolate Brownie | B34: 600 | D34: =VLOOKUP(B34,[1]ManipulationPage!$A$3:$D$541,4,FALSE) -> Baking | F34: Cake | G34: =VLOOKUP($F34,RecipeNotes!$A$2:$E$62,3,FALSE) -> Shortcut recipe: Fold the dry ingredients gently into the wet ingredients. Bake at 180°C until a toothpick inserted in the middle comes out clean (about 40 minutes). | H34: =VLOOKUP($F34,RecipeNotes!$A$2:$E$62,5,FALSE) -> Shortcut opskrift: Fold de tørre ingredienser ind i de våde. Bag i ovnen indtil en tandstik kan komme ud af dem uden dej sidder fast (ca 40 minutter).
A35: Chocolate Chip Banana Bread | B35: 429 | C35: 3037 | D35: =VLOOKUP(B35,[1]ManipulationPage!$A$3:$D$541,4,FALSE) -> Baking | F35: Banana bread | G35: =VLOOKUP($F35,RecipeNotes!$A$2:$E$62,3,FALSE) -> Shortcut recipe: Beat in the wet ingredients into the dry until no flour pockets remain. Do not overmix. Bake for 60 minutes (180 degrees) | H35: =VLOOKUP($F35,RecipeNotes!$A$2:$E$62,5,FALSE) -> Shortcut opskrift: Slå de våde ingredienser indi de tørre indtil der ikke er flere 'mel-lommer' i dejen. Bag i ca 60 minutter (180 grader). | I35: Banana bread with a chocolate twist. | J35: Bananbrød med et chokoladetwist. | K35: Banana bread with a chocolate twist.
A36: Chocolate Mousse | B36: 687 | C36: 3534 | D36: =VLOOKUP(B36,[1]ManipulationPage!$A$3:$D$541,4,FALSE) -> Baking | G36: =VLOOKUP($F36,RecipeNotes!$A$2:$E$62,3,FALSE) -> #N/A | H36: =VLOOKUP($F36,RecipeNotes!$A$2:$E$62,5,FALSE) -> #N/A | I36: Enjoy a rich and creamy chocolate mousse, aired to perfection!
A37: Cinnamon Swirls | B37: 477 | C37: 3118 | D37: =VLOOKUP(B37,[1]ManipulationPage!$A$3:$D$541,4,FALSE) -> Baking | G37: =VLOOKUP($F37,RecipeNotes!$A$2:$E$62,3,FALSE) -> #N/A | H37: =VLOOKUP($F37,RecipeNotes!$A$2:$E$62,5,FALSE) -> #N/A | I37: These cinnamon buns will have your kitchen smelling like heaven! | J37: Disse kanelsnegle vil få dit køkken til at dufte himmelsk! | K37: These cinnamon buns will have your kitchen smelling like heaven!
A38: Classic bundt cake | B38: 676 | C38: 3511 | D38: =VLOOKUP(B38,[1]ManipulationPage!$A$3:$D$541,4,FALSE) -> Baking | F38: Cake | G38: =VLOOKUP($F38,RecipeNotes!$A$2:$E$62,3,FALSE) -> Shortcut recipe: Fold the dry ingredients gently into the wet ingredients. Bake at 180°C until a toothpick inserted in the middle comes out clean (about 40 minutes). | H38: =VLOOKUP($F38,RecipeNotes!$A$2:$E$62,5,FALSE) -> Shortcut opskrift: Fold de tørre ingredienser ind i de våde. Bag i ovnen indtil en tandstik kan komme ud af dem uden dej sidder fast (ca 40 minutter).
A39: Classic bundt cake | B39: 685 | C39: 3529 | D39: =VLOOKUP(B39,[1]ManipulationPage!$A$3:$D$541,4,FALSE) -> Baking | F39: Cake | G39: =VLOOKUP($F39,RecipeNotes!$A$2:$E$62,3,FALSE) -> Shortcut recipe: Fold the dry ingredients gently into the wet ingredients. Bake at 180°C until a toothpick inserted in the middle comes out clean (about 40 minutes). | H39: =VLOOKUP($F39,RecipeNotes!$A$2:$E$62,5,FALSE) -> Shortcut opskrift: Fold de tørre ingredienser ind i de våde. Bag i ovnen indtil en tandstik kan komme ud af dem uden dej sidder fast (ca 40 minutter).
A40: Classic Cheesecake | B40: 391 | C40: 2937 | D40: =VLOOKUP(B40,[1]ManipulationPage!$A$3:$D$541,4,FALSE) -> Baking | F40: Cheesecake | G40: =VLOOKUP($F40,RecipeNotes!$A$2:$E$62,3,FALSE) -> Shortcut recipe: Bake crust for 10 minutes, then add 'cheese' in the springform, and bake for another 45 minutes. Put in fridge overnight. | H40: =VLOOKUP($F40,RecipeNotes!$A$2:$E$62,5,FALSE) -> Shortcut opskrift: Bag dejen i 10 minutter, tilføj derefter ost i springformen og bag i yderligere 45 mintter. Put i køleren over natten. | I40: It's cheesecake time! | J40: Det er cheesecake tid! | K40: It's cheesecake time!
A41: Cocoa Muffins | B41: 375 | C41: 2893 | D41: =VLOOKUP(B41,[1]ManipulationPage!$A$3:$D$541,4,FALSE) -> Baking | F41: Sweet muffin | G41: =VLOOKUP($F41,RecipeNotes!$A$2:$E$62,3,FALSE) -> Shortcut recipe: Gently mix the wet ingredients into the dry. Bake in oven until a toothpick comes out clean when pricking them (about 30 minutes) | H41: =VLOOKUP($F41,RecipeNotes!$A$2:$E$62,5,FALSE) -> Shortcut opskrift: Ælt de våde ingredienser indi i de tørre nænsomt. Bag i ovnen indtil en tandstik kan komme ud af dem uden dej sidder fast. | I41: Is it really dessert if there's no chocolate...? | J41: Er det virkelig en dessert, hvis den ikke indeholder chokolade...? | K41: Ist es wirklich ein Dessert, wenn es keine Schokolade enthält ...?
A42: Coconut Muesli Bar | B42: 433 | C42: 3045 | D42: =VLOOKUP(B42,[1]ManipulationPage!$A$3:$D$541,4,FALSE) -> Baking | G42: =VLOOKUP($F42,RecipeNotes!$A$2:$E$62,3,FALSE) -> #N/A | H42: =VLOOKUP($F42,RecipeNotes!$A$2:$E$62,5,FALSE) -> #N/A | I42: Coconut gives these muesli bars a tropical twist. | J42: Kokos giver disse müslibarer en tropisk twist. | K42: Coconut gives these muesli bars a tropical twist.
A43: Coconut Pecan Granola | B43: 407 | C43: 2980 | D43: =VLOOKUP(B43,[1]ManipulationPage!$A$3:$D$541,4,FALSE) -> Baking | G43: =VLOOKUP($F43,RecipeNotes!$A$2:$E$62,3,FALSE) -> #N/A | H43: =VLOOKUP($F43,RecipeNotes!$A$2:$E$62,5,FALSE) -> #N/A | I43: Mix your favorite seeds, dried fruits or other flavorings with oats, then bake them up for a deliciously crunchy breakfast option. | J43: Mix your favorite seeds, dried fruits or other flavorings with oats, then bake them up for a deliciously crunchy breakfast option. | K43: Mix your favorite seeds, dried fruits or other flavorings with oats, then bake them up for a deliciously crunchy breakfast option.
A44: Covered apple pie | B44: 673 | C44: 3505 | D44: =VLOOKUP(B44,[1]ManipulationPage!$A$3:$D$541,4,FALSE) -> Baking | G44: =VLOOKUP($F44,RecipeNotes!$A$2:$E$62,3,FALSE) -> #N/A | H44: =VLOOKUP($F44,RecipeNotes!$A$2:$E$62,5,FALSE) -> #N/A
A45: Covered apple pie | B45: 684 | C45: 3527 | D45: =VLOOKUP(B45,[1]ManipulationPage!$A$3:$D$541,4,FALSE) -> Baking | G45: =VLOOKUP($F45,RecipeNotes!$A$2:$E$62,3,FALSE) -> #N/A | H45: =VLOOKUP($F45,RecipeNotes!$A$2:$E$62,5,FALSE) -> #N/A
A46: Cranberry Almond Granola Bar | B46: 431 | C46: 3043 | D46: =VLOOKUP(B46,[1]ManipulationPage!$A$3:$D$541,4,FALSE) -> Baking | G46: =VLOOKUP($F46,RecipeNotes!$A$2:$E$62,3,FALSE) -> #N/A | H46: =VLOOKUP($F46,RecipeNotes!$A$2:$E$62,5,FALSE) -> #N/A | I46: Sweet and tart cranberries are a burst of flavor in these muesli bars. | J46: Søde og syrlige tranebær er en bombe af smag i disse müslibarer. | K46: Sweet and tart cranberries are a burst of flavor in these muesli bars.
A47: Creamy Baileys Mascarpone Dip | B47: 695 | C47: 3555 | D47: =VLOOKUP(B47,[1]ManipulationPage!$A$3:$D$541,4,FALSE) -> Baking | G47: =VLOOKUP($F47,RecipeNotes!$A$2:$E$62,3,FALSE) -> #N/A | H47: =VLOOKUP($F47,RecipeNotes!$A$2:$E$62,5,FALSE) -> #N/A | I47: Dip your favorite cookies and fruits into this creamy deliciousness!
A48: Dark Romance Infused Pancakes | B48: 658 | C48: 3469 | D48: =VLOOKUP(B48,[1]ManipulationPage!$A$3:$D$541,4,FALSE) -> Baking | F48: Pancakes | G48: =VLOOKUP($F48,RecipeNotes!$A$2:$E$62,3,FALSE) -> Shortcut recipe: Mix ingredients gently in a bowl. Heat a pan with oil or butter. Add in thin layers. 2 minutes per side. | H48: =VLOOKUP($F48,RecipeNotes!$A$2:$E$62,5,FALSE) -> Shortcut opskrift: Bland ingredienserne nænsomt i en skål. Varn en pande med olie/smør og tilføj dejen i små lag. 2 minutter per side.
A49: Espresso Chocolate Cake | B49: 453 | C49: 3074 | D49: =VLOOKUP(B49,[1]ManipulationPage!$A$3:$D$541,4,FALSE) -> Baking | F49: Cake | G49: =VLOOKUP($F49,RecipeNotes!$A$2:$E$62,3,FALSE) -> Shortcut recipe: Fold the dry ingredients gently into the wet ingredients. Bake at 180°C until a toothpick inserted in the middle comes out clean (about 40 minutes). | H49: =VLOOKUP($F49,RecipeNotes!$A$2:$E$62,5,FALSE) -> Shortcut opskrift: Fold de tørre ingredienser ind i de våde. Bag i ovnen indtil en tandstik kan komme ud af dem uden dej sidder fast (ca 40 minutter). | I49: Coffee and chocolate lovers, this one is for you. | J49: Kaffe og chokolade elskere, det her er for dig. | K49: Coffee and chocolate lovers, this one is for you.
A50: French Toast | B50: 1157 | C50: 10277 | D50: =VLOOKUP(B50,[1]ManipulationPage!$A$3:$D$541,4,FALSE) -> Baking | G50: =VLOOKUP($F50,RecipeNotes!$A$2:$E$62,3,FALSE) -> #N/A | H50: =VLOOKUP($F50,RecipeNotes!$A$2:$E$62,5,FALSE) -> #N/A | I50: Experiment with different bread types for various flavors.
A51: Fruit & Cream Cake | B51: 417 | C51: 3005 | D51: =VLOOKUP(B51,[1]ManipulationPage!$A$3:$D$541,4,FALSE) -> Baking | F51: Cake | G51: =VLOOKUP($F51,RecipeNotes!$A$2:$E$62,3,FALSE) -> Shortcut recipe: Fold the dry ingredients gently into the wet ingredients. Bake at 180°C until a toothpick inserted in the middle comes out clean (about 40 minutes). | H51: =VLOOKUP($F51,RecipeNotes!$A$2:$E$62,5,FALSE) -> Shortcut opskrift: Fold de tørre ingredienser ind i de våde. Bag i ovnen indtil en tandstik kan komme ud af dem uden dej sidder fast (ca 40 minutter). | I51: Choose fruits that are in season for the best flavor experience. | J51: Vælg frugt i sæson for den bedste smagsoplevelse. | K51: Choose fruits that are in season for the best flavor experience.
A52: Gingerbread cookies | B52: 621 | D52: =VLOOKUP(B52,[1]ManipulationPage!$A$3:$D$541,4,FALSE) -> Baking | F52: Cookies | G52: =VLOOKUP($F52,RecipeNotes!$A$2:$E$62,3,FALSE) -> Shortcut recipe: Drop spoonfuls of dough onto a baking sheet, evenly spaced out. Bake for 10 minutes at 160°C. The cookies will still be soft, but will firm up during cooling. | H52: =VLOOKUP($F52,RecipeNotes!$A$2:$E$62,5,FALSE) -> Shortcut opskrift: Drop skefulde dej på et bagepapir fordelt ligeligt. Bag ved 160 grader i 10 mintter. De vil være bløde først men fastere, når de køler ned.
A53: Gluten Free Bread | B53: 1148 | C53: 10079 | D53: =VLOOKUP(B53,[1]ManipulationPage!$A$3:$D$541,4,FALSE) -> Baking | F53: Bread | G53: =VLOOKUP($F53,RecipeNotes!$A$2:$E$62,3,FALSE) -> Shortcut recipe: knead in the wet ingredients into the dry until no flour pockets remain. Raise for 5 hours and bake for 1 hour (180 degrees). | H53: =VLOOKUP($F53,RecipeNotes!$A$2:$E$62,5,FALSE) -> Shortcut opskrift: Ælt de våde ingredienser indi ide tørre, indtil der ikke er mel-lommer. Hæv i mindst 5 timer, bag i ovnen i en time (180 grader). | I53: If you follow a gluten-free diet - it does NOT mean you have to miss out on delicious bread! | J53: If you follow a gluten-free diet - it does NOT mean you have to miss out on delicious bread! | K53: If you follow a gluten-free diet - it does NOT mean you have to miss out on delicious bread!
A54: Gluten Free "Rye Bread" | B54: 517 | C54: 3194 | D54: =VLOOKUP(B54,[1]ManipulationPage!$A$3:$D$541,4,FALSE) -> Baking | F54: Bread | G54: =VLOOKUP($F54,RecipeNotes!$A$2:$E$62,3,FALSE) -> Shortcut recipe: knead in the wet ingredients into the dry until no flour pockets remain. Raise for 5 hours and bake for 1 hour (180 degrees). | H54: =VLOOKUP($F54,RecipeNotes!$A$2:$E$62,5,FALSE) -> Shortcut opskrift: Ælt de våde ingredienser indi ide tørre, indtil der ikke er mel-lommer. Hæv i mindst 5 timer, bag i ovnen i en time (180 grader).
A55: Gluten-Free Seed Crackers | B55: 419 | C55: 3009 | D55: =VLOOKUP(B55,[1]ManipulationPage!$A$3:$D$541,4,FALSE) -> Baking | G55: =VLOOKUP($F55,RecipeNotes!$A$2:$E$62,3,FALSE) -> #N/A | H55: =VLOOKUP($F55,RecipeNotes!$A$2:$E$62,5,FALSE) -> #N/A | I55: Savory crackers made from wholesome ingredients | J55: Lækkert knækbrød lavet af sunde ingredienser | K55: Savory crackers made from wholesome ingredients
A56: Grandma's Carinthian cake | B56: 683 | C56: 3525 | D56: =VLOOKUP(B56,[1]ManipulationPage!$A$3:$D$541,4,FALSE) -> Baking | F56: Cake | G56: =VLOOKUP($F56,RecipeNotes!$A$2:$E$62,3,FALSE) -> Shortcut recipe: Fold the dry ingredients gently into the wet ingredients. Bake at 180°C until a toothpick inserted in the middle comes out clean (about 40 minutes). | H56: =VLOOKUP($F56,RecipeNotes!$A$2:$E$62,5,FALSE) -> Shortcut opskrift: Fold de tørre ingredienser ind i de våde. Bag i ovnen indtil en tandstik kan komme ud af dem uden dej sidder fast (ca 40 minutter).
A57: Grandma's Carinthian cake | B57: 672 | C57: 3503 | D57: =VLOOKUP(B57,[1]ManipulationPage!$A$3:$D$541,4,FALSE) -> Baking | F57: Cake | G57: =VLOOKUP($F57,RecipeNotes!$A$2:$E$62,3,FALSE) -> Shortcut recipe: Fold the dry ingredients gently into the wet ingredients. Bake at 180°C until a toothpick inserted in the middle comes out clean (about 40 minutes). | H57: =VLOOKUP($F57,RecipeNotes!$A$2:$E$62,5,FALSE) -> Shortcut opskrift: Fold de tørre ingredienser ind i de våde. Bag i ovnen indtil en tandstik kan komme ud af dem uden dej sidder fast (ca 40 minutter).
A58: Healthy Muffin | B58: 110 | C58: 1547 | D58: =VLOOKUP(B58,[1]ManipulationPage!$A$3:$D$541,4,FALSE) -> Baking | F58: Muffin | G58: =VLOOKUP($F58,RecipeNotes!$A$2:$E$62,3,FALSE) -> Shortcut recipe: Gently mix the wet ingredients into the dry. Bake in oven until a toothpick comes out clean when pricking them (about 30 minutes) | H58: =VLOOKUP($F58,RecipeNotes!$A$2:$E$62,5,FALSE) -> Shortcut opskrift: Ælt de våde ingredienser indi i de tørre nænsomt. Bag i ovnen indtil en tandstik kan komme ud af dem uden dej sidder fast. | I58: Muffins are super versatile - add anything you'd like, and Plant Jammer will make sure you get the baking ratios right. | J58: Muffins er super alsidige - tilføj lige det du har lyst til, og så skal Plant Jammer nok sørge for, at du bager med den rigtig ingrediensforhold. | K58: Muffins are super versatile - add anything you'd like, and Plant Jammer will make sure you get the baking ratios right.
A59: Homemade Pizza Dough | B59: 245 | C59: 2344 | D59: =VLOOKUP(B59,[1]ManipulationPage!$A$3:$D$541,4,FALSE) -> Baking | G59: =VLOOKUP($F59,RecipeNotes!$A$2:$E$62,3,FALSE) -> #N/A | H59: =VLOOKUP($F59,RecipeNotes!$A$2:$E$62,5,FALSE) -> #N/A | I59: It's important to knead your dough into a smooth consistency to make sure all the flour proteins create bonds. | J59: Det er vigtigt at ælte din dej til den får en jævn konsistens for at sikre, at alle mel proteiner skaber bindinger. | K59: It's important to knead your dough into a smooth consistency to make sure all the flour proteins create bonds.
A60: Jalapeño Corn Muffins | B60: 367 | C60: 2872 | D60: =VLOOKUP(B60,[1]ManipulationPage!$A$3:$D$541,4,FALSE) -> Baking | F60: Muffin | G60: =VLOOKUP($F60,RecipeNotes!$A$2:$E$62,3,FALSE) -> Shortcut recipe: Gently mix the wet ingredients into the dry. Bake in oven until a toothpick comes out clean when pricking them (about 30 minutes) | H60: =VLOOKUP($F60,RecipeNotes!$A$2:$E$62,5,FALSE) -> Shortcut opskrift: Ælt de våde ingredienser indi i de tørre nænsomt. Bag i ovnen indtil en tandstik kan komme ud af dem uden dej sidder fast. | I60: In a quick muffin, the veggies will help make your muffins moist. | J60: I en ’hurtig muffin’ vil vandet fra grøntsagerne gøre dine muffins fugtige. | K60: In a quick muffin, the veggies will help make your muffins moist.
A61: Key Lime Pie | B61: 689 | C61: 3539 | D61: =VLOOKUP(B61,[1]ManipulationPage!$A$3:$D$541,4,FALSE) -> Baking | G61: =VLOOKUP($F61,RecipeNotes!$A$2:$E$62,3,FALSE) -> #N/A | H61: =VLOOKUP($F61,RecipeNotes!$A$2:$E$62,5,FALSE) -> #N/A
A62: Layered cream cake | B62: 745 | C62: 3662 | D62: =VLOOKUP(B62,[1]ManipulationPage!$A$3:$D$541,4,FALSE) -> Baking | F62: Cake | G62: =VLOOKUP($F62,RecipeNotes!$A$2:$E$62,3,FALSE) -> Shortcut recipe: Fold the dry ingredients gently into the wet ingredients. Bake at 180°C until a toothpick inserted in the middle comes out clean (about 40 minutes). | H62: =VLOOKUP($F62,RecipeNotes!$A$2:$E$62,5,FALSE) -> Shortcut opskrift: Fold de tørre ingredienser ind i de våde. Bag i ovnen indtil en tandstik kan komme ud af dem uden dej sidder fast (ca 40 minutter).
A63: Lemon Coconut Energy Balls | B63: 441 | C63: 3056 | D63: =VLOOKUP(B63,[1]ManipulationPage!$A$3:$D$541,4,FALSE) -> Baking | F63: Energy balls | G63: =VLOOKUP($F63,RecipeNotes!$A$2:$E$62,3,FALSE) -> Shortcut recipe: Mash until reaches a cookie dough-like consistency. Add a little more wet or dry ingredients if needed to get the right texture. Form into balls and enjoy! | H63: =VLOOKUP($F63,RecipeNotes!$A$2:$E$62,5,FALSE) -> Shortcut opskrift: Ælt indtil konsistensen minder om kagedej. Form indtil kugler. | I63: These energy balls contain a bright burst of citrus flavor. | J63: Disse energikugler indeholder en frisk og kraftig citronsmag. | K63: These energy balls contain a bright burst of citrus flavor.
A64: Lemon poppy seed cake | B64: 718 | C64: 3606 | D64: =VLOOKUP(B64,[1]ManipulationPage!$A$3:$D$541,4,FALSE) -> Baking | F64: Cake | G64: =VLOOKUP($F64,RecipeNotes!$A$2:$E$62,3,FALSE) -> Shortcut recipe: Fold the dry ingredients gently into the wet ingredients. Bake at 180°C until a toothpick inserted in the middle comes out clean (about 40 minutes). | H64: =VLOOKUP($F64,RecipeNotes!$A$2:$E$62,5,FALSE) -> Shortcut opskrift: Fold de tørre ingredienser ind i de våde. Bag i ovnen indtil en tandstik kan komme ud af dem uden dej sidder fast (ca 40 minutter).
A65: Muffins | B65: 813 | C65: 3802 | D65: =VLOOKUP(B65,[1]ManipulationPage!$A$3:$D$541,4,FALSE) -> Baking | F65: Muffin | G65: =VLOOKUP($F65,RecipeNotes!$A$2:$E$62,3,FALSE) -> Shortcut recipe: Gently mix the wet ingredients into the dry. Bake in oven until a toothpick comes out clean when pricking them (about 30 minutes) | H65: =VLOOKUP($F65,RecipeNotes!$A$2:$E$62,5,FALSE) -> Shortcut opskrift: Ælt de våde ingredienser indi i de tørre nænsomt. Bag i ovnen indtil en tandstik kan komme ud af dem uden dej sidder fast. | I65: Soft and tender muffins can be made to fit for almost any occasion! Breakfast, snack, dessert, dinner...you name it! | J65: Soft and tender muffins can be made to fit for almost any occasion! Breakfast, snack, dessert, dinner...you name it! | K65: Soft and tender muffins can be made to fit for almost any occasion! Breakfast, snack, dessert, dinner...you name it!
A66: Mushroom Toast | B66: 575 | D66: =VLOOKUP(B66,[1]ManipulationPage!$A$3:$D$541,4,FALSE) -> Baking | G66: =VLOOKUP($F66,RecipeNotes!$A$2:$E$62,3,FALSE) -> #N/A | H66: =VLOOKUP($F66,RecipeNotes!$A$2:$E$62,5,FALSE) -> #N/A
A67: New York Cheesecake | B67: 671 | C67: 3501 | D67: =VLOOKUP(B67,[1]ManipulationPage!$A$3:$D$541,4,FALSE) -> Baking | F67: Cheesecake | G67: =VLOOKUP($F67,RecipeNotes!$A$2:$E$62,3,FALSE) -> Shortcut recipe: Bake crust for 10 minutes, then add 'cheese' in the springform, and bake for another 45 minutes. Put in fridge overnight. | H67: =VLOOKUP($F67,RecipeNotes!$A$2:$E$62,5,FALSE) -> Shortcut opskrift: Bag dejen i 10 minutter, tilføj derefter ost i springformen og bag i yderligere 45 mintter. Put i køleren over natten.
A68: New York Cheesecake | B68: 681 | C68: 3521 | D68: =VLOOKUP(B68,[1]ManipulationPage!$A$3:$D$541,4,FALSE) -> Baking | F68: Cheesecake | G68: =VLOOKUP($F68,RecipeNotes!$A$2:$E$62,3,FALSE) -> Shortcut recipe: Bake crust for 10 minutes, then add 'cheese' in the springform, and bake for another 45 minutes. Put in fridge overnight. | H68: =VLOOKUP($F68,RecipeNotes!$A$2:$E$62,5,FALSE) -> Shortcut opskrift: Bag dejen i 10 minutter, tilføj derefter ost i springformen og bag i yderligere 45 mintter. Put i køleren over natten.
A69: No-bake Cheesecake | B69: 401 | C69: 2964 | D69: =VLOOKUP(B69,[1]ManipulationPage!$A$3:$D$541,4,FALSE) -> Baking | F69: Cheesecake | G69: =VLOOKUP($F69,RecipeNotes!$A$2:$E$62,3,FALSE) -> Shortcut recipe: Bake crust for 10 minutes, then add 'cheese' in the springform, and bake for another 45 minutes. Put in fridge overnight. | H69: =VLOOKUP($F69,RecipeNotes!$A$2:$E$62,5,FALSE) -> Shortcut opskrift: Bag dejen i 10 minutter, tilføj derefter ost i springformen og bag i yderligere 45 mintter. Put i køleren over natten. | I69: It's cheesecake time! | J69: Det er cheesecake tid! | K69: It's cheesecake time!
A70: No Processed Sugar Muffins | B70: 373 | C70: 2889 | D70: =VLOOKUP(B70,[1]ManipulationPage!$A$3:$D$541,4,FALSE) -> Baking | F70: Sweet muffin | G70: =VLOOKUP($F70,RecipeNotes!$A$2:$E$62,3,FALSE) -> Shortcut recipe: Gently mix the wet ingredients into the dry. Bake in oven until a toothpick comes out clean when pricking them (about 30 minutes) | H70: =VLOOKUP($F70,RecipeNotes!$A$2:$E$62,5,FALSE) -> Shortcut opskrift: Ælt de våde ingredienser indi i de tørre nænsomt. Bag i ovnen indtil en tandstik kan komme ud af dem uden dej sidder fast. | I70: Soft and tender muffins can be made to fit for almost any occasion! Breakfast, snack, dessert, dinner...you name it! | J70: Soft and tender muffins can be made to fit for almost any occasion! Breakfast, snack, dessert, dinner...you name it! | K70: Soft and tender muffins can be made to fit for almost any occasion! Breakfast, snack, dessert, dinner...you name it!
A71: Nut Butter Cookies | B71: 397 | C71: 2951 | D71: =VLOOKUP(B71,[1]ManipulationPage!$A$3:$D$541,4,FALSE) -> Baking | F71: Cookies | G71: =VLOOKUP($F71,RecipeNotes!$A$2:$E$62,3,FALSE) -> Shortcut recipe: Drop spoonfuls of dough onto a baking sheet, evenly spaced out. Bake for 10 minutes at 160°C. The cookies will still be soft, but will firm up during cooling. | H71: =VLOOKUP($F71,RecipeNotes!$A$2:$E$62,5,FALSE) -> Shortcut opskrift: Drop skefulde dej på et bagepapir fordelt ligeligt. Bag ved 160 grader i 10 mintter. De vil være bløde først men fastere, når de køler ned. | I71: A classic sweet treat. | J71: En klassisk sød godbit. | K71: A classic sweet treat.
A72: Nutty Chocolate Muffins | B72: 465 | C72: 3096 | D72: =VLOOKUP(B72,[1]ManipulationPage!$A$3:$D$541,4,FALSE) -> Baking | F72: Sweet muffin | G72: =VLOOKUP($F72,RecipeNotes!$A$2:$E$62,3,FALSE) -> Shortcut recipe: Gently mix the wet ingredients into the dry. Bake in oven until a toothpick comes out clean when pricking them (about 30 minutes) | H72: =VLOOKUP($F72,RecipeNotes!$A$2:$E$62,5,FALSE) -> Shortcut opskrift: Ælt de våde ingredienser indi i de tørre nænsomt. Bag i ovnen indtil en tandstik kan komme ud af dem uden dej sidder fast. | I72: If you have your Batter Base on hand, skip straight to 🌀Twist It. | J72: Hvis du allerede har forberedt din Flydende Dej, så spring direkte videre til 🌀Twist It. | K72: If you have your Batter Base on hand, skip straight to 🌀Twist It.
A73: Oat Muffins | B73: 379 | C73: 2908 | D73: =VLOOKUP(B73,[1]ManipulationPage!$A$3:$D$541,4,FALSE) -> Baking | F73: Muffin | G73: =VLOOKUP($F73,RecipeNotes!$A$2:$E$62,3,FALSE) -> Shortcut recipe: Gently mix the wet ingredients into the dry. Bake in oven until a toothpick comes out clean when pricking them (about 30 minutes) | H73: =VLOOKUP($F73,RecipeNotes!$A$2:$E$62,5,FALSE) -> Shortcut opskrift: Ælt de våde ingredienser indi i de tørre nænsomt. Bag i ovnen indtil en tandstik kan komme ud af dem uden dej sidder fast. | I73: Soft and tender muffins can be made to fit for almost any occasion! Breakfast, snack, dessert, dinner...you name it! | J73: Soft and tender muffins can be made to fit for almost any occasion! Breakfast, snack, dessert, dinner...you name it! | K73: Soft and tender muffins can be made to fit for almost any occasion! Breakfast, snack, dessert, dinner...you name it!
A74: Overnight Oats | B74: 73 | C74: 1367 | D74: =VLOOKUP(B74,[1]ManipulationPage!$A$3:$D$541,4,FALSE) -> Baking | F74: Overnight oats | G74: =VLOOKUP($F74,RecipeNotes!$A$2:$E$62,3,FALSE) -> Shortcut recipe: Leave oats in liquids over night in the fridge (at least 3 hours). You can still gently heat it next day if you prefer it warm. | H74: =VLOOKUP($F74,RecipeNotes!$A$2:$E$62,5,FALSE) -> Shortcut opskrift: Læg havren i blød over natten i køleren. Du kan stadig varme grøden næste morgen, hvis du foretrækker den varm. | I74: Let the fridge do all the work for you. Wake up to a delicious, chilled breakfast! | J74: Lad køleskabet gøre alt arbejdet for dig. Vågn op til en lækker, kold morgenmad. | K74: Dein Kühlschrank macht die Arbeit - wache auf zu einem fertigen Powerfrühstück!
A75: Overnight Oats with Hemp | B75: 907 | C75: 4025 | D75: =VLOOKUP(B75,[1]ManipulationPage!$A$3:$D$541,4,FALSE) -> Baking | F75: Overnight oats | G75: =VLOOKUP($F75,RecipeNotes!$A$2:$E$62,3,FALSE) -> Shortcut recipe: Leave oats in liquids over night in the fridge (at least 3 hours). You can still gently heat it next day if you prefer it warm. | H75: =VLOOKUP($F75,RecipeNotes!$A$2:$E$62,5,FALSE) -> Shortcut opskrift: Læg havren i blød over natten i køleren. Du kan stadig varme grøden næste morgen, hvis du foretrækker den varm.
A76: Peanut Butter Bars | B76: 435 | C76: 3049 | D76: =VLOOKUP(B76,[1]ManipulationPage!$A$3:$D$541,4,FALSE) -> Baking | G76: =VLOOKUP($F76,RecipeNotes!$A$2:$E$62,3,FALSE) -> #N/A | H76: =VLOOKUP($F76,RecipeNotes!$A$2:$E$62,5,FALSE) -> #N/A | I76: Coconut gives these muesli bars a tropical twist. | J76: Kokos giver disse müslibarer en tropisk twist. | K76: Coconut gives these muesli bars a tropical twist.
A77: Pesto Garlic Swirls | B77: 479 | C77: 3122 | D77: =VLOOKUP(B77,[1]ManipulationPage!$A$3:$D$541,4,FALSE) -> Baking | G77: =VLOOKUP($F77,RecipeNotes!$A$2:$E$62,3,FALSE) -> #N/A | H77: =VLOOKUP($F77,RecipeNotes!$A$2:$E$62,5,FALSE) -> #N/A | I77: Get creative with sauce, topping, and cheese choices! | J77: Vær kreativ med dit valg af sovs, toppings og ost! | K77: Get creative with sauce, topping, and cheese choices!
A78: Pumpkin Nut Cake | B78: 449 | C78: 3068 | D78: =VLOOKUP(B78,[1]ManipulationPage!$A$3:$D$541,4,FALSE) -> Baking | F78: Cake | G78: =VLOOKUP($F78,RecipeNotes!$A$2:$E$62,3,FALSE) -> Shortcut recipe: Fold the dry ingredients gently into the wet ingredients. Bake at 180°C until a toothpick inserted in the middle comes out clean (about 40 minutes). | H78: =VLOOKUP($F78,RecipeNotes!$A$2:$E$62,5,FALSE) -> Shortcut opskrift: Fold de tørre ingredienser ind i de våde. Bag i ovnen indtil en tandstik kan komme ud af dem uden dej sidder fast (ca 40 minutter). | I78: Vegetables can indeed be used in cake! | J78: Grøntsager kan sagtens bruges i kage! | K78: Vegetables can indeed be used in cake!
A79: Quick Soda Bread | B79: 511 | C79: 3182 | D79: =VLOOKUP(B79,[1]ManipulationPage!$A$3:$D$541,4,FALSE) -> Baking | G79: =VLOOKUP($F79,RecipeNotes!$A$2:$E$62,3,FALSE) -> #N/A | H79: =VLOOKUP($F79,RecipeNotes!$A$2:$E$62,5,FALSE) -> #N/A | I79: Quick breads are an easy way to start baking your own bread - no kneading or leavening required. | J79: Quick breads are an easy way to start baking your own bread - no kneading or leavening required. | K79: Quick breads are an easy way to start baking your own bread - no kneading or leavening required.
A80: Red Velvet Cake | B80: 713 | C80: 3598 | D80: =VLOOKUP(B80,[1]ManipulationPage!$A$3:$D$541,4,FALSE) -> Baking | F80: Cake | G80: =VLOOKUP($F80,RecipeNotes!$A$2:$E$62,3,FALSE) -> Shortcut recipe: Fold the dry ingredients gently into the wet ingredients. Bake at 180°C until a toothpick inserted in the middle comes out clean (about 40 minutes). | H80: =VLOOKUP($F80,RecipeNotes!$A$2:$E$62,5,FALSE) -> Shortcut opskrift: Fold de tørre ingredienser ind i de våde. Bag i ovnen indtil en tandstik kan komme ud af dem uden dej sidder fast (ca 40 minutter). | I80: This classic cake is unbelievably moist, fluffy, flavorful, and perfectly red.
A81: Rhubarb and mango jam | B81: 1023 | C81: 6298 | D81: =VLOOKUP(B81,[1]ManipulationPage!$A$3:$D$541,4,FALSE) -> Baking | G81: =VLOOKUP($F81,RecipeNotes!$A$2:$E$62,3,FALSE) -> #N/A | H81: =VLOOKUP($F81,RecipeNotes!$A$2:$E$62,5,FALSE) -> #N/A
A82: Rhubarb Cake | B82: 413 | C82: 2995 | D82: =VLOOKUP(B82,[1]ManipulationPage!$A$3:$D$541,4,FALSE) -> Baking | F82: Cake | G82: =VLOOKUP($F82,RecipeNotes!$A$2:$E$62,3,FALSE) -> Shortcut recipe: Fold the dry ingredients gently into the wet ingredients. Bake at 180°C until a toothpick inserted in the middle comes out clean (about 40 minutes). | H82: =VLOOKUP($F82,RecipeNotes!$A$2:$E$62,5,FALSE) -> Shortcut opskrift: Fold de tørre ingredienser ind i de våde. Bag i ovnen indtil en tandstik kan komme ud af dem uden dej sidder fast (ca 40 minutter). | I82: Enhance this cake with frosting, fruits, whipped cream, nuts, chocolate... or anything else your sweet tooth craves! | J82: Du kan pynte med frosting, frugt, flødeskum, nødder, chokolade... eller hvad nu ellers din søde tand drømmer om! | K82: Enhance this cake with frosting, fruits, whipped cream, nuts, chocolate... or anything else your sweet tooth craves!
A83: Rhubarb curd | B83: 1028 | C83: 6308 | D83: =VLOOKUP(B83,[1]ManipulationPage!$A$3:$D$541,4,FALSE) -> Baking | G83: =VLOOKUP($F83,RecipeNotes!$A$2:$E$62,3,FALSE) -> #N/A | H83: =VLOOKUP($F83,RecipeNotes!$A$2:$E$62,5,FALSE) -> #N/A
A84: Rhubarb jelly with elderflower | B84: 1027 | C84: 6306 | D84: =VLOOKUP(B84,[1]ManipulationPage!$A$3:$D$541,4,FALSE) -> Baking | G84: =VLOOKUP($F84,RecipeNotes!$A$2:$E$62,3,FALSE) -> #N/A | H84: =VLOOKUP($F84,RecipeNotes!$A$2:$E$62,5,FALSE) -> #N/A
A85: Rhubarb syrup | B85: 871 | C85: 3928 | D85: =VLOOKUP(B85,[1]ManipulationPage!$A$3:$D$541,4,FALSE) -> Baking | G85: =VLOOKUP($F85,RecipeNotes!$A$2:$E$62,3,FALSE) -> #N/A | H85: =VLOOKUP($F85,RecipeNotes!$A$2:$E$62,5,FALSE) -> #N/A
A86: Rice Pudding | B86: 711 | C86: 3588 | D86: =VLOOKUP(B86,[1]ManipulationPage!$A$3:$D$541,4,FALSE) -> Baking | G86: =VLOOKUP($F86,RecipeNotes!$A$2:$E$62,3,FALSE) -> #N/A | H86: =VLOOKUP($F86,RecipeNotes!$A$2:$E$62,5,FALSE) -> #N/A | I86: Use short grain white rice for the creamiest results.
A87: Root Vegetable Muffins | B87: 38 | C87: 1181 | D87: =VLOOKUP(B87,[1]ManipulationPage!$A$3:$D$541,4,FALSE) -> Baking | F87: Muffin | G87: =VLOOKUP($F87,RecipeNotes!$A$2:$E$62,3,FALSE) -> Shortcut recipe: Gently mix the wet ingredients into the dry. Bake in oven until a toothpick comes out clean when pricking them (about 30 minutes) | H87: =VLOOKUP($F87,RecipeNotes!$A$2:$E$62,5,FALSE) -> Shortcut opskrift: Ælt de våde ingredienser indi i de tørre nænsomt. Bag i ovnen indtil en tandstik kan komme ud af dem uden dej sidder fast. | I87: Muffins are super versatile - add anything you'd like, and Plant Jammer will make sure you get the baking ratios right. | J87: Muffins er super alsidige - tilføj lige det du har lyst til, og så skal Plant Jammer nok sørge for, at du bager med den rigtig ingrediensforhold. | K87: Muffins are super versatile - add anything you'd like, and Plant Jammer will make sure you get the baking ratios right.
A88: Rye Bread | B88: 579 | D88: =VLOOKUP(B88,[1]ManipulationPage!$A$3:$D$541,4,FALSE) -> Baking | F88: Bread | G88: =VLOOKUP($F88,RecipeNotes!$A$2:$E$62,3,FALSE) -> Shortcut recipe: knead in the wet ingredients into the dry until no flour pockets remain. Raise for 5 hours and bake for 1 hour (180 degrees). | H88: =VLOOKUP($F88,RecipeNotes!$A$2:$E$62,5,FALSE) -> Shortcut opskrift: Ælt de våde ingredienser indi ide tørre, indtil der ikke er mel-lommer. Hæv i mindst 5 timer, bag i ovnen i en time (180 grader).
A89: Rye Bread | B89: 515 | C89: 3190 | D89: =VLOOKUP(B89,[1]ManipulationPage!$A$3:$D$541,4,FALSE) -> Baking | F89: Bread | G89: =VLOOKUP($F89,RecipeNotes!$A$2:$E$62,3,FALSE) -> Shortcut recipe: knead in the wet ingredients into the dry until no flour pockets remain. Raise for 5 hours and bake for 1 hour (180 degrees). | H89: =VLOOKUP($F89,RecipeNotes!$A$2:$E$62,5,FALSE) -> Shortcut opskrift: Ælt de våde ingredienser indi ide tørre, indtil der ikke er mel-lommer. Hæv i mindst 5 timer, bag i ovnen i en time (180 grader). | I89: Rye bread is a Nordic classic - dense yet moist and soft, with a hearty and seedy taste. It's perfect for breakfast, lunch, or dinner! | J89: Rye bread is a Nordic classic - dense yet moist and soft, with a hearty and seedy taste. It's perfect for breakfast, lunch, or dinner! | K89: Rye bread is a Nordic classic - dense yet moist and soft, with a hearty and seedy taste. It's perfect for breakfast, lunch, or dinner!
A90: Rye Sesame Seed Crackers | B90: 409 | C90: 2988 | D90: =VLOOKUP(B90,[1]ManipulationPage!$A$3:$D$541,4,FALSE) -> Baking | G90: =VLOOKUP($F90,RecipeNotes!$A$2:$E$62,3,FALSE) -> #N/A | H90: =VLOOKUP($F90,RecipeNotes!$A$2:$E$62,5,FALSE) -> #N/A | I90: Savory crackers made from wholesome ingredients | J90: Lækkert knækbrød lavet af sunde ingredienser | K90: Savory crackers made from wholesome ingredients
A91: Savory Bread Pudding | B91: 423 | C91: 3018 | D91: =VLOOKUP(B91,[1]ManipulationPage!$A$3:$D$541,4,FALSE) -> Baking | G91: =VLOOKUP($F91,RecipeNotes!$A$2:$E$62,3,FALSE) -> #N/A | H91: =VLOOKUP($F91,RecipeNotes!$A$2:$E$62,5,FALSE) -> #N/A | I91: Experiment with different bread types for various flavors.
A92: Savory Zucchini Muffins | B92: 497 | C92: 3144 | D92: =VLOOKUP(B92,[1]ManipulationPage!$A$3:$D$541,4,FALSE) -> Baking | F92: Muffin | G92: =VLOOKUP($F92,RecipeNotes!$A$2:$E$62,3,FALSE) -> Shortcut recipe: Gently mix the wet ingredients into the dry. Bake in oven until a toothpick comes out clean when pricking them (about 30 minutes) | H92: =VLOOKUP($F92,RecipeNotes!$A$2:$E$62,5,FALSE) -> Shortcut opskrift: Ælt de våde ingredienser indi i de tørre nænsomt. Bag i ovnen indtil en tandstik kan komme ud af dem uden dej sidder fast. | I92: In a quick muffin, the veggies will help make your muffins moist. | J92: I en ’hurtig muffin’ vil vandet fra grøntsagerne gøre dine muffins fugtige. | K92: In a quick muffin, the veggies will help make your muffins moist.
A93: Scones | B93: 425 | C93: 3026 | D93: =VLOOKUP(B93,[1]ManipulationPage!$A$3:$D$541,4,FALSE) -> Baking | G93: =VLOOKUP($F93,RecipeNotes!$A$2:$E$62,3,FALSE) -> #N/A | H93: =VLOOKUP($F93,RecipeNotes!$A$2:$E$62,5,FALSE) -> #N/A | I93: Scones can vary by region. These are crumbly and rich American-style scones. | J93: Scones kan variere fra sted til sted. Disse er de smuldrende og mættende amerikansk scones. | K93: Scones can vary by region. These are crumbly and rich American-style scones.
A94: Sesame Snaps | B94: 712 | C94: 3591 | D94: =VLOOKUP(B94,[1]ManipulationPage!$A$3:$D$541,4,FALSE) -> Baking | G94: =VLOOKUP($F94,RecipeNotes!$A$2:$E$62,3,FALSE) -> #N/A | H94: =VLOOKUP($F94,RecipeNotes!$A$2:$E$62,5,FALSE) -> #N/A | I94: The thinner you roll out the Sesame Snaps, the crunchier they get!
A95: Simple Paleo Cupcake | B95: 574 | C95: 3256 | D95: =VLOOKUP(B95,[1]ManipulationPage!$A$3:$D$541,4,FALSE) -> Baking | G95: =VLOOKUP($F95,RecipeNotes!$A$2:$E$62,3,FALSE) -> #N/A | H95: =VLOOKUP($F95,RecipeNotes!$A$2:$E$62,5,FALSE) -> #N/A | I95: It's best to use coconut cream from a carton rather than a tin. This diminishes the risk of contamination that you would get from coconut cream stored in aluminium tins.
A96: Snowball coconut bites | B96: 625 | D96: =VLOOKUP(B96,[1]ManipulationPage!$A$3:$D$541,4,FALSE) -> Baking | G96: =VLOOKUP($F96,RecipeNotes!$A$2:$E$62,3,FALSE) -> #N/A | H96: =VLOOKUP($F96,RecipeNotes!$A$2:$E$62,5,FALSE) -> #N/A
A97: sourdough bread | B97: 385 | C97: 2918 | D97: =VLOOKUP(B97,[1]ManipulationPage!$A$3:$D$541,4,FALSE) -> Baking | F97: Bread | G97: =VLOOKUP($F97,RecipeNotes!$A$2:$E$62,3,FALSE) -> Shortcut recipe: knead in the wet ingredients into the dry until no flour pockets remain. Raise for 5 hours and bake for 1 hour (180 degrees). | H97: =VLOOKUP($F97,RecipeNotes!$A$2:$E$62,5,FALSE) -> Shortcut opskrift: Ælt de våde ingredienser indi ide tørre, indtil der ikke er mel-lommer. Hæv i mindst 5 timer, bag i ovnen i en time (180 grader). | I97: Sourdough bread uses wild yeast for the leavening, resulting in a more complex flavor. | J97: Surdejsbrød bruger vild gær som hævemiddel, hvilket resulterer i en mere kompleks smag. | K97: Sourdough bread uses wild yeast for the leavening, resulting in a more complex flavor.
A98: Sourdough Rye Bread | B98: 509 | C98: 3178 | D98: =VLOOKUP(B98,[1]ManipulationPage!$A$3:$D$541,4,FALSE) -> Baking | F98: Bread | G98: =VLOOKUP($F98,RecipeNotes!$A$2:$E$62,3,FALSE) -> Shortcut recipe: knead in the wet ingredients into the dry until no flour pockets remain. Raise for 5 hours and bake for 1 hour (180 degrees). | H98: =VLOOKUP($F98,RecipeNotes!$A$2:$E$62,5,FALSE) -> Shortcut opskrift: Ælt de våde ingredienser indi ide tørre, indtil der ikke er mel-lommer. Hæv i mindst 5 timer, bag i ovnen i en time (180 grader). | I98: Rye bread is a Nordic classic - dense yet moist and soft, with a hearty and seedy taste. It's perfect for breakfast, lunch, or dinner! | J98: Rye bread is a Nordic classic - dense yet moist and soft, with a hearty and seedy taste. It's perfect for breakfast, lunch, or dinner! | K98: Rye bread is a Nordic classic - dense yet moist and soft, with a hearty and seedy taste. It's perfect for breakfast, lunch, or dinner!
A99: Strawberry Traybake Cake | B99: 677 | C99: 3513 | D99: =VLOOKUP(B99,[1]ManipulationPage!$A$3:$D$541,4,FALSE) -> Baking | F99: Cake | G99: =VLOOKUP($F99,RecipeNotes!$A$2:$E$62,3,FALSE) -> Shortcut recipe: Fold the dry ingredients gently into the wet ingredients. Bake at 180°C until a toothpick inserted in the middle comes out clean (about 40 minutes). | H99: =VLOOKUP($F99,RecipeNotes!$A$2:$E$62,5,FALSE) -> Shortcut opskrift: Fold de tørre ingredienser ind i de våde. Bag i ovnen indtil en tandstik kan komme ud af dem uden dej sidder fast (ca 40 minutter).
A100: Vegan Apple Cake | B100: 415 | C100: 3000 | D100: =VLOOKUP(B100,[1]ManipulationPage!$A$3:$D$541,4,FALSE) -> Baking | F100: Cake | G100: =VLOOKUP($F100,RecipeNotes!$A$2:$E$62,3,FALSE) -> Shortcut recipe: Fold the dry ingredients gently into the wet ingredients. Bake at 180°C until a toothpick inserted in the middle comes out clean (about 40 minutes). | H100: =VLOOKUP($F100,RecipeNotes!$A$2:$E$62,5,FALSE) -> Shortcut opskrift: Fold de tørre ingredienser ind i de våde. Bag i ovnen indtil en tandstik kan komme ud af dem uden dej sidder fast (ca 40 minutter). | I100: Apples give both moisture and a bit of tartness to this delicious dessert. | J100: Apples give both moisture and a bit of tartness to this delicious dessert. | K100: Apples give both moisture and a bit of tartness to this delicious dessert.
...

Sheet RecipeNotes
A1: Resulting notes
A2: Stir-Fry | B2: =CookingComponents!B2&" "&CookingComponents!B8&" "&CookingComponents!B16&" "&CookingComponents!B21&" "&CookingComponents!B25&" "&CookingComponents!B26&" "&CookingComponents!B28 -> Fry your onions and spices with a bit of oil. Add your condiments. Add veggies to the pan. Cook your other ingredients on the side. Once all your ingredients are cooked and ready to eat, mix them. Before toppings, taste and balance your dish by adding salt, sugar, sour, or umami ingredients for increased flavor. Too sour? Add salt and sugar. Too spicy? Add oil and sugar. Too Salty? Add bitter ingredients or fresh herbs. Add toppings and enjoy! | C2: =CookingComponents!C2&" "&CookingComponents!C8&" "&CookingComponents!C25 -> Shortcut recipe: Fry onions and spices on a pan. Add veggies. Taste and balance with salt, sugar, sour, and umami. | D2: =LEN(C2) -> 114 | E2: =CookingComponents!E2&" "&CookingComponents!E8&" "&CookingComponents!E25 -> Shortcut opskrift: Steg løg og krydderier på panden. Tilføj grøntsager Smag til med salt, sukker, syre og umami.
A3: With noodles/grains | B3: =CookingComponents!B2&" "&CookingComponents!B8&" "&CookingComponents!B22&" "&CookingComponents!B25&" "&CookingComponents!B26&" "&CookingComponents!B28 -> Fry your onions and spices with a bit of oil. Add your condiments. Add veggies to the pan. Mix all your ingredients with your boiled grains/noodles. Before toppings, taste and balance your dish by adding salt, sugar, sour, or umami ingredients for increased flavor. Too sour? Add salt and sugar. Too spicy? Add oil and sugar. Too Salty? Add bitter ingredients or fresh herbs. Add toppings and enjoy! | C3: =CookingComponents!C2&" "&CookingComponents!C8&" "&CookingComponents!C22 -> Shortcut recipe: Fry onions and spices on a pan. Add veggies. Mix with cooked grains/noodles. | D3: =LEN(C3) -> 93 | E3: =CookingComponents!E2&" "&CookingComponents!E8&" "&CookingComponents!E22 -> Shortcut opskrift: Steg løg og krydderier på panden. Tilføj grøntsager Bland med kogte nudler/bælgfrugter/korn.
A4: Pasta | B4: =CookingComponents!B2&" "&CookingComponents!B8&" "&CookingComponents!B23&" "&CookingComponents!B25&" "&CookingComponents!B26&" "&CookingComponents!B28 -> Fry your onions and spices with a bit of oil. Add your condiments. Add veggies to the pan. Add 1/2 cup of the pasta water to the frying pan for a creamier consistency. Mix all your ingredients with your boiled pasta. Before toppings, taste and balance your dish by adding salt, sugar, sour, or umami ingredients for increased flavor. Too sour? Add salt and sugar. Too spicy? Add oil and sugar. Too Salty? Add bitter ingredients or fresh herbs. Add toppings and enjoy! | C4: =CookingComponents!C2&" "&CookingComponents!C23 -> Shortcut recipe: Fry onions and spices on a pan. Mix with cooked pasta, including a cup of the pasta water (for creamy consistency). | D4: =LEN(C4) -> 132 | E4: =CookingComponents!E2&" "&CookingComponents!E23 -> Shortcut opskrift: Steg løg og krydderier på panden. Ibland den kogte pasta med en kop pasta vand.
A5: Salad | B5: =CookingComponents!B10&" "&CookingComponents!B17&" "&CookingComponents!B25&" "&CookingComponents!B26&" "&CookingComponents!B28 -> Wash, cut and mix your base ingredients. Mix in your dressing: Oil, sour ingredients, salt, and sugar. Before toppings, taste and balance your dish by adding salt, sugar, sour, or umami ingredients for increased flavor. Too sour? Add salt and sugar. Too spicy? Add oil and sugar. Too Salty? Add bitter ingredients or fresh herbs. Add toppings and enjoy! | C5: =CookingComponents!C10&" "&CookingComponents!C25&" "&CookingComponents!C26&" "&CookingComponents!C28 -> Shortcut recipe: Cut and mix all ingredients. Taste and balance with salt, sugar, sour, and umami. | D5: =LEN(C5) -> 100 | E5: =CookingComponents!E10&" "&CookingComponents!E25&" "&CookingComponents!E26&" "&CookingComponents!E28 -> Shortcut opskrift: Skær og bland alle ingredienser. Smag til med salt, sukker, syre og umami.
A6: Omelette | B6: =CookingComponents!B2&" "&CookingComponents!B8&" "&CookingComponents!B13&" "&CookingComponents!B14&" "&CookingComponents!B28 -> Fry your onions and spices with a bit of oil. Add your condiments. Add veggies to the pan. Crack the eggs into a bowl and whisk well with salt and pepper, before adding to the pan. Run a spatula through the middle of the omelette and tilt the pan to fill up with the runny egg. Omelette is done when there's no more runny egg. Add toppings and enjoy! | C6: =CookingComponents!C2&" "&CookingComponents!C13&" "&CookingComponents!C14 -> Shortcut recipe: Fry onions and spices on a pan. Whisk eggs well with salt, then add to pan. Omelette is done when egg isn't runny. | D6: =LEN(C6) -> 131 | E6: =CookingComponents!E2&" "&CookingComponents!E13&" "&CookingComponents!E14 -> Shortcut opskrift: Steg løg og krydderier på panden. Bland æg grundigt med salt og andre smags-ingredienser. Tilføj så til panden. Omeletten er klar, når ægget ikke løber længere.
A7: Pizza | C7: =CookingComponents!C35 -> Shortcut recipe: Make your suco of fried onions, spices, and your choice of paste. Add to pizza with your choice of veggies. | D7: =LEN(C7) -> 124 | E7: =CookingComponents!E35 -> Shortcut opskrift: Smør din pizza sauce i tyndt lag (lavet af løg, krydderier og din sauce stegt på en pande). Tilføj dine grøntsager på toppen.
A8: Risotto | B8: =CookingComponents!B2&" "&CookingComponents!B7&" "&CookingComponents!B16&" "&CookingComponents!B21&" "&CookingComponents!B25&" "&CookingComponents!B26&" "&CookingComponents!B28 -> Fry your onions and spices with a bit of oil. Add your condiments. Add risotto rice to the pan and then slowly add water or stock while stirring. Cook your other ingredients on the side. Once all your ingredients are cooked and ready to eat, mix them. Before toppings, taste and balance your dish by adding salt, sugar, sour, or umami ingredients for increased flavor. Too sour? Add salt and sugar. Too spicy? Add oil and sugar. Too Salty? Add bitter ingredients or fresh herbs. Add toppings and enjoy! | C8: =CookingComponents!C2&" "&CookingComponents!C7&" "&CookingComponents!C16&" "&CookingComponents!C21 -> Shortcut recipe: Fry onions and spices on a pan. Add rice with a little wine, then add stock and boiling water gradually. | D8: =LEN(C8) -> 123 | E8: =CookingComponents!E2&" "&CookingComponents!E7&" "&CookingComponents!E16&" "&CookingComponents!E21 -> Shortcut opskrift: Steg løg og krydderier på panden. Tilføj ris med en smule vin. Tilføj kogende vand med buillon gradvist.
A9: Creamy soup | B9: =CookingComponents!B2&" "&CookingComponents!B8&" "&CookingComponents!B18&" "&CookingComponents!B19&" "&CookingComponents!B25&" "&CookingComponents!B26&" "&CookingComponents!B28 -> Fry your onions and spices with a bit of oil. Add your condiments. Add veggies to the pan. Add water with stock/broth. Add a splash of oil, then blend into your desired consistency. Before toppings, taste and balance your dish by adding salt, sugar, sour, or umami ingredients for increased flavor. Too sour? Add salt and sugar. Too spicy? Add oil and sugar. Too Salty? Add bitter ingredients or fresh herbs. Add toppings and enjoy! | C9: =CookingComponents!C2&" "&CookingComponents!C8&" "&CookingComponents!C18&" "&CookingComponents!C19&" "&CookingComponents!C25 -> Shortcut recipe: Fry onions and spices on a pan. Add veggies. Add water with stock/broth. Blend the soup. Taste and balance with salt, sugar, sour, and umami. | D9: =LEN(C9) -> 158 | E9: =CookingComponents!E2&" "&CookingComponents!E8&" "&CookingComponents!E18&" "&CookingComponents!E19&" "&CookingComponents!E25 -> Shortcut opskrift: Steg løg og krydderier på panden. Tilføj grøntsager Til føj vand med buillon. Blend suppen. Smag til med salt, sukker, syre og umami.
A10: Chunky soup | B10: =CookingComponents!B2&" "&CookingComponents!B8&" "&CookingComponents!B18&" "&CookingComponents!B25&" "&CookingComponents!B26&" "&CookingComponents!B28 -> Fry your onions and spices with a bit of oil. Add your condiments. Add veggies to the pan. Add water with stock/broth. Before toppings, taste and balance your dish by adding salt, sugar, sour, or umami ingredients for increased flavor. Too sour? Add salt and sugar. Too spicy? Add oil and sugar. Too Salty? Add bitter ingredients or fresh herbs. Add toppings and enjoy! | C10: =CookingComponents!C2&" "&CookingComponents!C8&" "&CookingComponents!C18&" "&CookingComponents!C25&" "&CookingComponents!C26&" "&CookingComponents!C28 -> Shortcut recipe: Fry onions and spices on a pan. Add veggies. Add water with stock/broth. Taste and balance with salt, sugar, sour, and umami. | D10: =LEN(C10) -> 144 | E10: =CookingComponents!E2&" "&CookingComponents!E8&" "&CookingComponents!E18&" "&CookingComponents!E25&" "&CookingComponents!E26&" "&CookingComponents!E28 -> Shortcut opskrift: Steg løg og krydderier på panden. Tilføj grøntsager Til føj vand med buillon. Smag til med salt, sukker, syre og umami.
A11: Stew | B11: =CookingComponents!B2&" "&CookingComponents!B8&" "&CookingComponents!B18&" "&CookingComponents!B25&" "&CookingComponents!B26&" "&CookingComponents!B28 -> Fry your onions and spices with a bit of oil. Add your condiments. Add veggies to the pan. Add water with stock/broth. Before toppings, taste and balance your dish by adding salt, sugar, sour, or umami ingredients for increased flavor. Too sour? Add salt and sugar. Too spicy? Add oil and sugar. Too Salty? Add bitter ingredients or fresh herbs. Add toppings and enjoy! | C11: =CookingComponents!C2&" "&CookingComponents!C8&" "&CookingComponents!C18&" "&CookingComponents!C25&" "&CookingComponents!C26&" "&CookingComponents!C28 -> Shortcut recipe: Fry onions and spices on a pan. Add veggies. Add water with stock/broth. Taste and balance with salt, sugar, sour, and umami. | D11: =LEN(C11) -> 144 | E11: =CookingComponents!E2&" "&CookingComponents!E8&" "&CookingComponents!E18&" "&CookingComponents!E25&" "&CookingComponents!E26&" "&CookingComponents!E28 -> Shortcut opskrift: Steg løg og krydderier på panden. Tilføj grøntsager Til føj vand med buillon. Smag til med salt, sukker, syre og umami.
A12: Oven roast | B12: =CookingComponents!B9&" "&CookingComponents!B21&" "&CookingComponents!B25&" "&CookingComponents!B26&" "&CookingComponents!B28 -> Mix your veggies with onions, spices, salt, and oil. Roast at 180 degrees until desired color and texture. Once all your ingredients are cooked and ready to eat, mix them. Before toppings, taste and balance your dish by adding salt, sugar, sour, or umami ingredients for increased flavor. Too sour? Add salt and sugar. Too spicy? Add oil and sugar. Too Salty? Add bitter ingredients or fresh herbs. Add toppings and enjoy! | C12: =CookingComponents!C9&" "&CookingComponents!C21&" "&CookingComponents!C25&" "&CookingComponents!C26&" "&CookingComponents!C28 -> Shortcut recipe: Roast veggies with onion, spices, salt, and oil in the oven. Taste and balance with salt, sugar, sour, and umami. | D12: =LEN(C12) -> 133 | E12: =CookingComponents!E9&" "&CookingComponents!E21&" "&CookingComponents!E25&" "&CookingComponents!E26&" "&CookingComponents!E28 -> Shortcut opskrift: Læg grøntsagerne i ovnen med løg, krydderier, salt og olie. Smag til med salt, sukker, syre og umami.
A13: Daal | B13: =CookingComponents!B2&" "&CookingComponents!B11&" "&CookingComponents!B25&" "&CookingComponents!B26&" "&CookingComponents!B28 -> Fry your onions and spices with a bit of oil. Add your condiments. Add lentils to the pan, and then slowly add water or stock while stirring. Before toppings, taste and balance your dish by adding salt, sugar, sour, or umami ingredients for increased flavor. Too sour? Add salt and sugar. Too spicy? Add oil and sugar. Too Salty? Add bitter ingredients or fresh herbs. Add toppings and enjoy! | C13: =CookingComponents!C2&" "&CookingComponents!C11&" "&CookingComponents!C25&" "&CookingComponents!C26&" "&CookingComponents!C28 -> Shortcut recipe: Fry onions and spices on a pan. Add lentils, then water with stock. Taste and balance with salt, sugar, sour, and umami. | D13: =LEN(C13) -> 139 | E13: =CookingComponents!E2&" "&CookingComponents!E11&" "&CookingComponents!E25&" "&CookingComponents!E26&" "&CookingComponents!E28 -> Shortcut opskrift: Steg løg og krydderier på panden. Tilføj linser, dernæst vand med buillon. Smag til med salt, sukker, syre og umami.
A14: Panzanella | B14: =CookingComponents!B2&" "&CookingComponents!B8&" "&CookingComponents!B12&" "&CookingComponents!B21&" "&CookingComponents!B25&" "&CookingComponents!B26&" "&CookingComponents!B28 -> Fry your onions and spices with a bit of oil. Add your condiments. Add veggies to the pan. Cut your bread in small cubes, mix with oil, salt and pepper and bake in the oven for 10-15 minutes. Once all your ingredients are cooked and ready to eat, mix them. Before toppings, taste and balance your dish by adding salt, sugar, sour, or umami ingredients for increased flavor. Too sour? Add salt and sugar. Too spicy? Add oil and sugar. Too Salty? Add bitter ingredients or fresh herbs. Add toppings and enjoy! | C14: =CookingComponents!C12 -> Shortcut recipe: 50% is bread. Cut bread in cubes, drizzle with oil and salt, and then bake in oven. Cook and add your other ingredients | D14: =LEN(C14) -> 136 | E14: =CookingComponents!E12 -> Shortcut opskrift: 50% er brød. Skær brøddet i kvadrater, tilføj olie og salt og bag i ovnen. Tilføj til de andre ingredienser.
A15: Tagine | B15: =B11 -> Fry your onions and spices with a bit of oil. Add your condiments. Add veggies to the pan. Add water with stock/broth. Before toppings, taste and balance your dish by adding salt, sugar, sour, or umami ingredients for increased flavor. Too sour? Add salt and sugar. Too spicy? Add oil and sugar. Too Salty? Add bitter ingredients or fresh herbs. Add toppings and enjoy! | C15: =CookingComponents!C2&" "&CookingComponents!C8&" "&CookingComponents!C25 -> Shortcut recipe: Fry onions and spices on a pan. Add veggies. Taste and balance with salt, sugar, sour, and umami. | D15: =LEN(C15) -> 114 | E15: =CookingComponents!E2&" "&CookingComponents!E8&" "&CookingComponents!E25 -> Shortcut opskrift: Steg løg og krydderier på panden. Tilføj grøntsager Smag til med salt, sukker, syre og umami.
A16: Borscht | B16: =B9 -> Fry your onions and spices with a bit of oil. Add your condiments. Add veggies to the pan. Add water with stock/broth. Add a splash of oil, then blend into your desired consistency. Before toppings, taste and balance your dish by adding salt, sugar, sour, or umami ingredients for increased flavor. Too sour? Add salt and sugar. Too spicy? Add oil and sugar. Too Salty? Add bitter ingredients or fresh herbs. Add toppings and enjoy! | C16: =CookingComponents!C2&" "&CookingComponents!C33&" "&CookingComponents!C18&" "&CookingComponents!C19&" "&CookingComponents!C25 -> Shortcut recipe: Fry onions and spices on a pan. Add the beets Add water with stock/broth. Blend the soup. Taste and balance with salt, sugar, sour, and umami. | D16: =LEN(C16) -> 159 | E16: =CookingComponents!E2&" "&CookingComponents!E33&" "&CookingComponents!E18&" "&CookingComponents!E19&" "&CookingComponents!E25 -> Shortcut opskrift: Steg løg og krydderier på panden. Tilføj rødbederne. Til føj vand med buillon. Blend suppen. Smag til med salt, sukker, syre og umami.
A17: Fried rice | B17: =CookingComponents!B6&" "&CookingComponents!B2&" "&CookingComponents!B8&" "&CookingComponents!B22&" "&CookingComponents!B25&" "&CookingComponents!B26&" "&CookingComponents!B28 -> Boil your rice and let them cool. Fry your onions and spices with a bit of oil. Add your condiments. Add veggies to the pan. Mix all your ingredients with your boiled grains/noodles. Before toppings, taste and balance your dish by adding salt, sugar, sour, or umami ingredients for increased flavor. Too sour? Add salt and sugar. Too spicy? Add oil and sugar. Too Salty? Add bitter ingredients or fresh herbs. Add toppings and enjoy! | C17: =CookingComponents!C2&" "&CookingComponents!C35&" "&CookingComponents!C34 -> Shortcut recipe: Fry onions and spices on a pan. Shortcut recipe: Make your suco of fried onions, spices, and your choice of paste. Add to pizza with your choice of veggies. Add an umami sauce, sugar, and cold rice that was cooked the day before, and fry for a few more minutes. | D17: =LEN(C17) -> 278 | E17: =CookingComponents!E2&" "&CookingComponents!E35&" "&CookingComponents!E34 -> Shortcut opskrift: Steg løg og krydderier på panden. Shortcut opskrift: Smør din pizza sauce i tyndt lag (lavet af løg, krydderier og din sauce stegt på en pande). Tilføj dine grøntsager på toppen. Tilføj en umami sauce, sukker, og kold ris fra dagen før. Steg i et par minutter
A18: Tacos | C18: =CookingComponents!C2&" "&CookingComponents!C8&" "&CookingComponents!C25&" "&CookingComponents!C31 -> Shortcut recipe: Fry onions and spices on a pan. Add veggies. Taste and balance with salt, sugar, sour, and umami. Add all to the tacos. Enjoy! | D18: =LEN(C18) -> 143 | E18: =CookingComponents!E2&" "&CookingComponents!E8&" "&CookingComponents!E25&" "&CookingComponents!E31 -> Shortcut opskrift: Steg løg og krydderier på panden. Tilføj grøntsager Smag til med salt, sukker, syre og umami. Tilføj alt i dine tacos.
A19: Summer rolls | C19: =CookingComponents!C2&" "&CookingComponents!C8&" "&CookingComponents!C25&" "&CookingComponents!C32 -> Shortcut recipe: Fry onions and spices on a pan. Add veggies. Taste and balance with salt, sugar, sour, and umami. Soften rice paper in warm water, then fill with your ingredients. Enjoy! | D19: =LEN(C19) -> 187 | E19: =CookingComponents!E2&" "&CookingComponents!E8&" "&CookingComponents!E25&" "&CookingComponents!E32 -> Shortcut opskrift: Steg løg og krydderier på panden. Tilføj grøntsager Smag til med salt, sukker, syre og umami. Blødgør rispapiret i varmt vand, fyld så med dine ingredienser.
A20: Pilaf | C20: =CookingComponents!C2&" "&CookingComponents!C36 -> Shortcut recipe: Fry onions and spices on a pan. Add rice and toast them briefly. Then add water (with stock) to boil as usual. | D20: =LEN(C20) -> 127 | E20: =CookingComponents!E2&" "&CookingComponents!E36 -> Shortcut opskrift: Steg løg og krydderier på panden. Tilføj ris og rist dem kort. Tilføj vand med buillon og kog risene.
A21: Loaded potato | C21: =CookingComponents!C37 -> Shortcut recipe: Bake whole potato for up to an hour in oven, scoop out half the inside, and add your filling | D21: =LEN(C21) -> 109 | E21: =CookingComponents!E37 -> Shortcut opskrift: Bag den hele kartoffel i op til en time i ovnen. Grav halvdelen af indmaden ud og tilføj din filling.
A22: Polenta | C22: =CookingComponents!C38&" "&CookingComponents!C5&" "&CookingComponents!C25 -> Shortcut recipe: Whisk polenta into boiling water (with stock) bit-by-bit. Add your veggies and condiments. Taste and balance with salt, sugar, sour, and umami. | D22: =LEN(C22) -> 160 | E22: =CookingComponents!E38&" "&CookingComponents!E5&" "&CookingComponents!E25 -> Shortcut opskrift: Bag den hele kartoffel i op til en time i ovnen. Grav halvdelen af indmaden ud og tilføj din filling. Tilføj dine grøntsager og saucer. Smag til med salt, sukker, syre og umami.
A23: Wraps | C23: =CookingComponents!C2&" "&CookingComponents!C8&" "&CookingComponents!C25&" "&CookingComponents!C42&" "&CookingComponents!C43 -> Shortcut recipe: Fry onions and spices on a pan. Add veggies. Taste and balance with salt, sugar, sour, and umami. Pluck the leaves off your cabbage/lettuce, to be used as 'tacos'. Add all to the 'tacos'. Enjoy! | D23: =LEN(C23) -> 211 | E23: =CookingComponents!E2&" "&CookingComponents!E8&" "&CookingComponents!E25&" "&CookingComponents!E42&" "&CookingComponents!E43 -> Shortcut opskrift: Steg løg og krydderier på panden. Tilføj grøntsager Smag til med salt, sukker, syre og umami. Pluk bladene forsigtigt af dine kål/salat for at bruge dem som 'tacos'. Tilføj i din 'tacos'.
A24: Burrito | C24: =CookingComponents!C2&" "&CookingComponents!C8&" "&CookingComponents!C25&" "&CookingComponents!C44 -> Shortcut recipe: Fry onions and spices on a pan. Add veggies. Taste and balance with salt, sugar, sour, and umami. Add all in the burritos. Enjoy | D24: =LEN(C24) -> 145 | E24: =CookingComponents!E2&" "&CookingComponents!E8&" "&CookingComponents!E25&" "&CookingComponents!E44 -> Shortcut opskrift: Steg løg og krydderier på panden. Tilføj grøntsager Smag til med salt, sukker, syre og umami. Tilføj alt i dine burritos.
A25: Porridge | C25: =CookingComponents!C51 -> Shortcut recipe: Add boiling water to oats with a bit of salt. Wait 5 minutes. Then add your condiments | D25: =LEN(C25) -> 103 | E25: =CookingComponents!E51 -> Shortcut opskrift: Tilføj kogende vand og en smule salt - vent 5 minutter… vupti!
A26: Congee | C26: =CookingComponents!C2&" "&CookingComponents!C39&" "&CookingComponents!C25 -> Shortcut recipe: Fry onions and spices on a pan. Add rice and boiling water with stock, let simmer. Taste and balance with salt, sugar, sour, and umami. | D26: =LEN(C26) -> 152 | E26: =CookingComponents!E2&" "&CookingComponents!E39&" "&CookingComponents!E25 -> Shortcut opskrift: Steg løg og krydderier på panden. Tilføj ris og kogt vand med buillon og lad simre. Smag til med salt, sukker, syre og umami.
A27: Broccoli/cauliflower rice | C27: =CookingComponents!C40&" "&CookingComponents!C25 -> Shortcut recipe: Grate or use your food processor to make it into 'rice'. Add your spices and condiments. Taste and balance with salt, sugar, sour, and umami. | D27: =LEN(C27) -> 158 | E27: =CookingComponents!E40&" "&CookingComponents!E25 -> Shortcut opskrift: Riv eller brug food processeren til at lave 'ris' af din grøntsag. Tilføj dine andre ingredienser. Smag til med salt, sukker, syre og umami.
A28: Gazpacho | C28: =CookingComponents!C41&" "&CookingComponents!C25 -> Shortcut recipe: Add veggies with bread to a blender and pulse to the desired texture. Cool it down in fridge. Taste and balance with salt, sugar, sour, and umami. | D28: =LEN(C28) -> 163 | E28: =CookingComponents!E41&" "&CookingComponents!E25 -> Shortcut opskrift: Tilføj grøntsager med brød i blenderen og glend til din ønskede tekstur. Lad hvile i køleren i mindst en halv time. Smag til med salt, sukker, syre og umami.
A29: Mash | C29: =CookingComponents!C45 -> Shortcut recipe: Mash your veggie with a blender or fork, mixing in some oil or butter for creaminess. | D29: =LEN(C29) -> 102 | E29: =CookingComponents!E45 -> Shortcut opskrift: Blend dine grøntsager med lidt smør/olie med en gaffel eller en blender.
A30: Moussaka | C30: =CookingComponents!C46 -> Shortcut recipe: Alternate between layers of thin-sliced veggies and sauce. Bake in the oven for 30+ minutes (180 degrees). | D30: =LEN(C30) -> 123 | E30: =CookingComponents!E46 -> Shortcut opskrift: Skift mellem lag a tyndt skårne grøntsager og din sovs. Bag i ovnen i +30 minutter ved 180 grader.
A31: Lasagna | C31: =CookingComponents!C47 -> Shortcut recipe: Alternate between layers of pasta and sauce. Bake in the oven for 30+ minutes (180 degrees). | D31: =LEN(C31) -> 109 | E31: =CookingComponents!E47 -> Shortcut opskrift: Skift mellem lag a pasta og din sovs. Bag i ovnen i +30 minutter ved 180 grader.
A32: Casserole | C32: =CookingComponents!C48 -> Shortcut recipe: Put a layer of cooked grains on-top of your sauce. Bake in the oven for 30+ minutes (180 degrees) | D32: =LEN(C32) -> 114 | E32: =CookingComponents!E48 -> Shortcut opskrift: Put et lag af dine kogte korn på toppen. Bag i ovnen i +30 minutter ved 180 grader.
A33: Quiche | C33: =CookingComponents!C49 -> Shortcut recipe: Add your ingredients into a pie crust, then pour a whisked egg mixture on top. Bake for 30+ minutes (180 degrees). | D33: =LEN(C33) -> 131 | E33: =CookingComponents!E49 -> Shortcut opskrift: Tilføj dine ingredineser i din tærtedej. Hæld et rørt æg ind i blandingen. Bag i ovnen i +30 minutter ved 180 grader.
A34: Burger pattys | C34: =CookingComponents!C50 -> Shortcut recipe: Mash ingredients with a fork or a blender. Shape patties in your hands and fry them on a pan with oil (5 minutes on each side). | D34: =LEN(C34) -> 144 | E34: =CookingComponents!E50 -> Shortcut opskrift: Blend ingredienser med en gaffel eller blender. Form bøfferne i dine hænder og steg dem (5-10 minutter per side).
A35: Dip | C35: =CookingComponents!C52&" "&CookingComponents!C25 -> Shortcut recipe: Cook then mash with a blender or fork. Taste and balance with salt, sugar, sour, and umami. | D35: =LEN(C35) -> 108 | E35: =CookingComponents!E52&" "&CookingComponents!E25 -> Shortcut opskrift: Kog og blend derefter med en gaffel eller blender. Smag til med salt, sukker, syre og umami.
A36: Guacamole | C36: =CookingComponents!C53&" "&CookingComponents!C17 -> Shortcut recipe: Cut and mix ingredients. Mash with fork. Add oil, sours, salt, and sugar. | D36: =LEN(C36) -> 90 | E36: =CookingComponents!E53&" "&CookingComponents!E17 -> Shortcut opskrift: Skær og bland ingredienser. Blend med en gaffel eller blender. Smag til med olie, syre, salt og sukker.
A38: Rosti | C38: =CookingComponents!C55 -> Shortcut recipe: Grate ingredients and mix them with salt, flour, and eggs. Shape patties in your hands and fry them on a pan with oil (5 minutes on each side). | D38: =LEN(C38) -> 160 | E38: =CookingComponents!E55 -> Shortcut opskrift: Riv ingredienser og bland med salt, mel og æg. Form bøfferne i dine hænder og steg dem (5 minutter per side).
A39: Bread | C39: =CookingComponents!C56 -> Shortcut recipe: knead in the wet ingredients into the dry until no flour pockets remain. Raise for 5 hours and bake for 1 hour (180 degrees). | D39: =LEN(C39) -> 142 | E39: =CookingComponents!E56 -> Shortcut opskrift: Ælt de våde ingredienser indi ide tørre, indtil der ikke er mel-lommer. Hæv i mindst 5 timer, bag i ovnen i en time (180 grader).
A40: Marinade | C40: =CookingComponents!C57 -> Shortcut recipe: Mix ingredients and stir around with a fork. | D40: =LEN(C40) -> 61 | E40: =CookingComponents!E57 -> Shortcut opskrift: Bland ingredienser og rør rundt med en gaffel.
A41: Ratatouille | C41: =CookingComponents!C58 -> Shortcut recipe: You can both fry the veggies with onions and spices in the oven (25 minutes, 180 degrees) or the frying pan (15 minutes) | D41: =LEN(C41) -> 137 | E41: =CookingComponents!E58 -> Shortcut opskrift: Du kan både stege ingredienserne (15 minutter) eller bage dem i ovnen (25 minutter).
A42: Muffin | C42: =CookingComponents!C59 -> Shortcut recipe: Gently mix the wet ingredients into the dry. Bake in oven until a toothpick comes out clean when pricking them (about 30 minutes) | D42: =LEN(C42) -> 146 | E42: =CookingComponents!E59 -> Shortcut opskrift: Ælt de våde ingredienser indi i de tørre nænsomt. Bag i ovnen indtil en tandstik kan komme ud af dem uden dej sidder fast.
A43: Sweet muffin | C43: =CookingComponents!C60 -> Shortcut recipe: Gently mix the wet ingredients into the dry. Bake in oven until a toothpick comes out clean when pricking them (about 30 minutes) | D43: =LEN(C43) -> 146 | E43: =CookingComponents!E60 -> Shortcut opskrift: Ælt de våde ingredienser indi i de tørre nænsomt. Bag i ovnen indtil en tandstik kan komme ud af dem uden dej sidder fast.
A44: Pasta salad | C44: =CookingComponents!C2&" "&CookingComponents!C5&" "&CookingComponents!C61&" "&CookingComponents!C25 -> Shortcut recipe: Fry onions and spices on a pan. Add your veggies and condiments. Mix with cooked pasta. Taste and balance with salt, sugar, sour, and umami. | D44: =LEN(C44) -> 157 | E44: =CookingComponents!E2&" "&CookingComponents!E5&" "&CookingComponents!E61&" "&CookingComponents!E25 -> Shortcut opskrift: Steg løg og krydderier på panden. Tilføj dine grøntsager og saucer. Bland med kogt pasta. Smag til med salt, sukker, syre og umami.
A45: Buddha bowl | C45: =CookingComponents!C62 -> Shortcut recipe: Cook and arrange ingredients seperately in the bowl for a beautiful impression. | D45: =LEN(C45) -> 96 | E45: =CookingComponents!E62 -> Shortcut opskrift: Kog og arranger ingredienser adskilt og malerisk i en skål.
A46: Sandwich | C46: =CookingComponents!C63 -> Shortcut recipe: Prepare your ingredients seperately and add as layers on the bread. | D46: =LEN(C46) -> 84 | E46: =CookingComponents!E63 -> Shortcut opskrift: Forbered dine ingredienser sperat og put på brøddet i lag.
A47: Cake | C47: =CookingComponents!C64 -> Shortcut recipe: Fold the dry ingredients gently into the wet ingredients. Bake at 180°C until a toothpick inserted in the middle comes out clean (about 40 minutes). | D47: =LEN(C47) -> 165 | E47: =CookingComponents!E64 -> Shortcut opskrift: Fold de tørre ingredienser ind i de våde. Bag i ovnen indtil en tandstik kan komme ud af dem uden dej sidder fast (ca 40 minutter).
A48: Energy balls | C48: =CookingComponents!C65 -> Shortcut recipe: Mash until reaches a cookie dough-like consistency. Add a little more wet or dry ingredients if needed to get the right texture. Form into balls and enjoy! | D48: =LEN(C48) -> 172 | E48: =CookingComponents!E65 -> Shortcut opskrift: Ælt indtil konsistensen minder om kagedej. Form indtil kugler.
A49: Cheesecake | C49: =CookingComponents!C66 -> Shortcut recipe: Bake crust for 10 minutes, then add 'cheese' in the springform, and bake for another 45 minutes. Put in fridge overnight. | D49: =LEN(C49) -> 138 | E49: =CookingComponents!E66 -> Shortcut opskrift: Bag dejen i 10 minutter, tilføj derefter ost i springformen og bag i yderligere 45 mintter. Put i køleren over natten.
A50: cookies | C50: =CookingComponents!C67 -> Shortcut recipe: Drop spoonfuls of dough onto a baking sheet, evenly spaced out. Bake for 10 minutes at 160°C. The cookies will still be soft, but will firm up during cooling. | D50: =LEN(C50) -> 175 | E50: =CookingComponents!E67 -> Shortcut opskrift: Drop skefulde dej på et bagepapir fordelt ligeligt. Bag ved 160 grader i 10 mintter. De vil være bløde først men fastere, når de køler ned.
A51: Orzotto | C51: =CookingComponents!C2&" "&CookingComponents!C68 -> Shortcut recipe: Fry onions and spices on a pan. Add barley with a little wine, then add stock and boiling water gradually. | D51: =LEN(C51) -> 123 | E51: =CookingComponents!E2&" "&CookingComponents!E68 -> Shortcut opskrift: Steg løg og krydderier på panden. Tilføj byg med en smule vin. Tilføj så buillon og vand langsomt.
A52: Pancakes | C52: =CookingComponents!C69 -> Shortcut recipe: Mix ingredients gently in a bowl. Heat a pan with oil or butter. Add in thin layers. 2 minutes per side. | D52: =LEN(C52) -> 121 | E52: =CookingComponents!E69 -> Shortcut opskrift: Bland ingredienserne nænsomt i en skål. Varn en pande med olie/smør og tilføj dejen i små lag. 2 minutter per side.
A53: Falafel | C53: =CookingComponents!C4&" "&CookingComponents!C70 -> Shortcut recipe: Mash ingredients into a hummus with a fork or a blender. Shape patties in your hands and fry them on a pan with oil (5 minutes on each side). | D53: =LEN(C53) -> 159 | E53: =CookingComponents!E4&" "&CookingComponents!E70 -> Shortcut opskrift. Blend ingredienserne til hummus med en ske eller blender. Form bøfferne i hænderne og steg i olie ca 5 minutter per side.
A54: Hummus | C54: =CookingComponents!C5&" "&CookingComponents!C71 -> Add your veggies and condiments. Shortcut recipe: Mix cooked chickpeas with rest of ingredients. Mash with a blender or fork, and add salt and lemon to taste. | D54: =LEN(C54) -> 158 | E54: =CookingComponents!E5&" "&CookingComponents!E71 -> Tilføj dine grøntsager og saucer. Shortcut opskrift: Bland kogte kikærter med resten af ingredienserne. Blend med en gaffel eller blender. Smag til med citron og salt.
A55: Shakshouka | C55: =CookingComponents!C2&" "&CookingComponents!C5&" "&CookingComponents!C72 -> Shortcut recipe: Fry onions and spices on a pan. Add your veggies and condiments. Use your large spoon to make small wells in the sauce and crack the eggs into each well. Cover the pan and cook for 5-8 minutes. | D55: =LEN(C55) -> 210 | E55: =CookingComponents!E2&" "&CookingComponents!E5&" "&CookingComponents!E72 -> Shortcut opskrift: Steg løg og krydderier på panden. Tilføj dine grøntsager og saucer. Brug en stor ske til at lave små kanaler i suacen og hæld æggene deri. Put låg på og kog i 5-10 minutter.
A56: Stuffed Veggie | C56: =CookingComponents!C2&" "&CookingComponents!C73 -> Shortcut recipe: Fry onions and spices on a pan. Put all veggies and condiments into the veggie and roast it all in the oven for 20-30 minutes or until tender. | D56: =LEN(C56) -> 159 | E56: =CookingComponents!E2&" "&CookingComponents!E73 -> Shortcut opskrift: Steg løg og krydderier på panden. Put all grøntsager og krydderier ind i beholderen og bag i ovnen i 20-30 minutter.
A57: Tabbouleh | C57: =CookingComponents!C10&" "&CookingComponents!C74 -> Shortcut recipe: Cut and mix all ingredients. This dish should be a little fresh and sour. | D57: =LEN(C57) -> 90 | E57: =CookingComponents!E10&" "&CookingComponents!E74 -> Shortcut opskrift: Skær og bland alle ingredienser. Retten skal være en smule frisk og syrlig.
A58: Slaw | C58: =CookingComponents!C10&" "&CookingComponents!C75 -> Shortcut recipe: Cut and mix all ingredients. This dish should be a little fresh and sour. | D58: =LEN(C58) -> 90 | E58: =CookingComponents!E10&" "&CookingComponents!E75 -> Shortcut opskrift: Skær og bland alle ingredienser. Retten skal være en smule frisk og syrlig.
A59: Smoothie | C59: =CookingComponents!C76 -> Shortcut recipe: Mix and blend all ingredients. Store it in the fridge up to 3 days. Serve the smoothie cold. | D59: =LEN(C59) -> 109 | E59: =CookingComponents!E76 -> Shortcut opskrift: Bland og blend alle ingredienser. Opbevar i køleren op til 3 dage.
A60: Quesadilla | C60: =CookingComponents!C77 -> Shortcut recipe: Add fillings to your tortilla and fold over. Heat a bit of oil in your pan and cook the quesadilla for 2-3min per side until golden brown. | D60: =LEN(C60) -> 155 | E60: =CookingComponents!E77 -> Shortcut opskrift: Tilføj ingredienser til tortilla og fold dem. Varm en smule olie på en pande og steg quesadillas 2-3 minutter per side.
A61: Banana bread | C61: =CookingComponents!C78 -> Shortcut recipe: Beat in the wet ingredients into the dry until no flour pockets remain. Do not overmix. Bake for 60 minutes (180 degrees) | D61: =LEN(C61) -> 138 | E61: =CookingComponents!E78 -> Shortcut opskrift: Slå de våde ingredienser indi de tørre indtil der ikke er flere 'mel-lommer' i dejen. Bag i ca 60 minutter (180 grader).
A62: Overnight oats | C62: =CookingComponents!C79 -> Shortcut recipe: Leave oats in liquids over night in the fridge (at least 3 hours). You can still gently heat it next day if you prefer it warm. | D62: =LEN(C62) -> 144 | E62: =CookingComponents!E79 -> Shortcut opskrift: Læg havren i blød over natten i køleren. Du kan stadig varme grøden næste morgen, hvis du foretrækker den varm.

Sheet CookingComponents
A1: Modules | C1: Shorter version | E1: Da
A2: Sofrito | B2: Fry your onions and spices with a bit of oil. Add your condiments. | C2: Shortcut recipe: Fry onions and spices on a pan. | E2: Shortcut opskrift: Steg løg og krydderier på panden.
A3: Trick | B3: Add and evaporate a splash of alcohol among the spices to accentuate the aromas. | C3: Add a splash of alcohol to accentuate aromas | E3: Tilføj en smule alkohol for at vække aromaerne.
A5: Add | C5: Add your veggies and condiments. | E5: Tilføj dine grøntsager og saucer.
A6: Rice | B6: Boil your rice and let them cool. | C6: Shortcut recipe: Boil rice then let them cool. | E6: Shortcut opskrift: Kog ris og lad dem køle.
A7: Risotto | B7: Add risotto rice to the pan and then slowly add water or stock while stirring. | C7: Add rice with a little wine, then add stock and boiling water gradually. | E7: Tilføj ris med en smule vin. Tilføj kogende vand med buillon gradvist.
A8: Fry | B8: Add veggies to the pan. | C8: Add veggies. | E8: Tilføj grøntsager
A9: Roast | B9: Mix your veggies with onions, spices, salt, and oil. Roast at 180 degrees until desired color and texture. | C9: Shortcut recipe: Roast veggies with onion, spices, salt, and oil in the oven. | E9: Shortcut opskrift: Læg grøntsagerne i ovnen med løg, krydderier, salt og olie.
A10: Raw | B10: Wash, cut and mix your base ingredients. | C10: Shortcut recipe: Cut and mix all ingredients. | E10: Shortcut opskrift: Skær og bland alle ingredienser.
A11: Daal | B11: Add lentils to the pan, and then slowly add water or stock while stirring. | C11: Add lentils, then water with stock. | E11: Tilføj linser, dernæst vand med buillon.
A12: Panzanella | B12: Cut your bread in small cubes, mix with oil, salt and pepper and bake in the oven for 10-15 minutes. | C12: Shortcut recipe: 50% is bread. Cut bread in cubes, drizzle with oil and salt, and then bake in oven. Cook and add your other ingredients | E12: Shortcut opskrift: 50% er brød. Skær brøddet i kvadrater, tilføj olie og salt og bag i ovnen. Tilføj til de andre ingredienser.
A13: Omelette1 | B13: Crack the eggs into a bowl and whisk well with salt and pepper, before adding to the pan. | C13: Whisk eggs well with salt, then add to pan. | E13: Bland æg grundigt med salt og andre smags-ingredienser. Tilføj så til panden.
A14: Omelette2 | B14: Run a spatula through the middle of the omelette and tilt the pan to fill up with the runny egg. Omelette is done when there's no more runny egg. | C14: Omelette is done when egg isn't runny. | E14: Omeletten er klar, når ægget ikke løber længere.
A16: Other heating | B16: Cook your other ingredients on the side.
A17: Dressing | B17: Mix in your dressing: Oil, sour ingredients, salt, and sugar. | C17: Add oil, sours, salt, and sugar. | E17: Smag til med olie, syre, salt og sukker.
A18: Stock | B18: Add water with stock/broth. | C18: Add water with stock/broth. | E18: Til føj vand med buillon.
A19: Soup blending | B19: Add a splash of oil, then blend into your desired consistency. | C19: Blend the soup. | E19: Blend suppen.
A21: Mix | B21: Once all your ingredients are cooked and ready to eat, mix them.
A22: Mix if grains | B22: Mix all your ingredients with your boiled grains/noodles. | C22: Mix with cooked grains/noodles. | E22: Bland med kogte nudler/bælgfrugter/korn.
A23: Mix if pasta | B23: Add 1/2 cup of the pasta water to the frying pan for a creamier consistency. Mix all your ingredients with your boiled pasta. | C23: Mix with cooked pasta, including a cup of the pasta water (for creamy consistency). | E23: Ibland den kogte pasta med en kop pasta vand.
A25: Taste | B25: Before toppings, taste and balance your dish by adding salt, sugar, sour, or umami ingredients for increased flavor. | C25: Taste and balance with salt, sugar, sour, and umami. | E25: Smag til med salt, sukker, syre og umami.
A26: Balance | B26: Too sour? Add salt and sugar. Too spicy? Add oil and sugar. Too Salty? Add bitter ingredients or fresh herbs.
A28: Finish | B28: Add toppings and enjoy!
A30: Dish specific texts
A31: Tacos2 | B31: Add your ingredients and toppings to your taco. Enjoy! | C31: Add all to the tacos. Enjoy! | E31: Tilføj alt i dine tacos.
A32: Summer rolls | B32: Place the rice paper in warm water until softened; then lift out and add your ingredients and toppings before closing. Enjoy! | C32: Soften rice paper in warm water, then fill with your ingredients. Enjoy! | E32: Blødgør rispapiret i varmt vand, fyld så med dine ingredienser.
A33: Borscht | C33: Add the beets | E33: Tilføj rødbederne.
A34: Fried rice 1 | C34: Add an umami sauce, sugar, and cold rice that was cooked the day before, and fry for a few more minutes. | E34: Tilføj en umami sauce, sukker, og kold ris fra dagen før. Steg i et par minutter
A35: Pizza | C35: Shortcut recipe: Make your suco of fried onions, spices, and your choice of paste. Add to pizza with your choice of veggies. | E35: Shortcut opskrift: Smør din pizza sauce i tyndt lag (lavet af løg, krydderier og din sauce stegt på en pande). Tilføj dine grøntsager på toppen.
A36: Pilaf | C36: Add rice and toast them briefly. Then add water (with stock) to boil as usual. | E36: Tilføj ris og rist dem kort. Tilføj vand med buillon og kog risene.
A37: Loaded potato | C37: Shortcut recipe: Bake whole potato for up to an hour in oven, scoop out half the inside, and add your filling | E37: Shortcut opskrift: Bag den hele kartoffel i op til en time i ovnen. Grav halvdelen af indmaden ud og tilføj din filling.
A38: Polenta | C38: Shortcut recipe: Whisk polenta into boiling water (with stock) bit-by-bit. | E38: Shortcut opskrift: Bag den hele kartoffel i op til en time i ovnen. Grav halvdelen af indmaden ud og tilføj din filling.
A39: Congee | C39: Add rice and boiling water with stock, let simmer. | E39: Tilføj ris og kogt vand med buillon og lad simre.
A40: Broccoli/cauliflower rice | C40: Shortcut recipe: Grate or use your food processor to make it into 'rice'. Add your spices and condiments. | E40: Shortcut opskrift: Riv eller brug food processeren til at lave 'ris' af din grøntsag. Tilføj dine andre ingredienser.
A41: Gazpacho | C41: Shortcut recipe: Add veggies with bread to a blender and pulse to the desired texture. Cool it down in fridge. | E41: Shortcut opskrift: Tilføj grøntsager med brød i blenderen og glend til din ønskede tekstur. Lad hvile i køleren i mindst en halv time.
A42: Wraps 1 | C42: Pluck the leaves off your cabbage/lettuce, to be used as 'tacos'. | E42: Pluk bladene forsigtigt af dine kål/salat for at bruge dem som 'tacos'.
A43: Wraps 2 | C43: Add all to the 'tacos'. Enjoy! | E43: Tilføj i din 'tacos'.
A44: Burito | C44: Add all in the burritos. Enjoy | E44: Tilføj alt i dine burritos.
... A79: Overnight oats | C79: Shortcut recipe: Leave oats in liquids over night in the fridge (at least 3 hours). You can still gently heat it next day if you prefer it warm. | E79: Shortcut opskrift: Læg havren i blød over natten i køleren. Du kan stadig varme grøden næste morgen, hvis du foretrækker den varm.

Sheet DishDescriptions
A1: dish_name | B1: dish_pk | C1: mltext_pk | D1: Type | E1: New text | F1: en | G1: da | H1: de | I1: lv | J1: et | K1: lt | L1: es
A2: Pickling | B2: 141 | C2: 1740 | D2: =VLOOKUP(B2,[1]ManipulationPage!$A$3:$D$541,4,FALSE) -> 0 | E2: =IF(VLOOKUP(B2,DishNotes!$B$2:$E$573,4,FALSE)="!","!","") | F2: Add a pleasant sour flavor to any dish you make by pickling your favorite vegetables. | G2: Add a pleasant sour flavor to any dish you make by pickling your favorite vegetables. | H2: Add a pleasant sour flavor to any dish you make by pickling your favorite vegetables.
A3: Asian Marinade | B3: 1094 | C3: 9262 | D3: =VLOOKUP(B3,[1]ManipulationPage!$A$3:$D$541,4,FALSE) -> Asia | E3: =IF(VLOOKUP(B3,DishNotes!$B$2:$E$573,4,FALSE)="!","!","") | F3: Create a delicious marinade to give an Asian twist to your vegetables or tofu. | G3: Lav en lækker marinade for at give et asiatisk twist til dine grøntsager eller tofu. | H3: Stelle eine köstliche Marinade her, um deinem Gemüse oder Tofu eine asiatische Note zu verleihen.
A4: Asian Marinade | B4: 101 | C4: 1478 | D4: =VLOOKUP(B4,[1]ManipulationPage!$A$3:$D$541,4,FALSE) -> Asia | E4: =IF(VLOOKUP(B4,DishNotes!$B$2:$E$573,4,FALSE)="!","!","") | F4: Create a delicious marinade to give an Asian twist to your vegetables or tofu. | G4: Lav en lækker marinade for at give et asiatisk twist til dine grøntsager eller tofu. | H4: Stelle eine köstliche Marinade her, um deinem Gemüse oder Tofu eine asiatische Note zu verleihen.
A5: Asian Salad | B5: 988 | C5: 5419 | D5: =VLOOKUP(B5,[1]ManipulationPage!$A$3:$D$541,4,FALSE) -> Asia | E5: =IF(VLOOKUP(B5,DishNotes!$B$2:$E$573,4,FALSE)="!","!","") -> !
A6: Chow Mein | B6: 3 | C6: 976 | D6: =VLOOKUP(B6,[1]ManipulationPage!$A$3:$D$541,4,FALSE) -> Asia | E6: =IF(VLOOKUP(B6,DishNotes!$B$2:$E$573,4,FALSE)="!","!","") -> ! | F6: A noodle stir-fry dish that originated in China, which has been adopted throughout the Western world. | G6: En nuddel baseret wok-ret fra Kina, der er blevet adopteret overalt i verden. | H6: Chow Mein ist ein Nudelgericht der chinesisch-amerikanischen Küche und wird im Wok mit Gemüse gebraten.
A7: Congee | B7: 361 | C7: 3199 | D7: =VLOOKUP(B7,[1]ManipulationPage!$A$3:$D$541,4,FALSE) -> Asia | E7: =IF(VLOOKUP(B7,DishNotes!$B$2:$E$573,4,FALSE)="!","!","") -> ! | F7: Easy and cheap Asian porridge that tastes amazing. Topping is key!
A8: Japanese Omelette | B8: 31 | C8: 1134 | D8: =VLOOKUP(B8,[1]ManipulationPage!$A$3:$D$541,4,FALSE) -> Asia | E8: =IF(VLOOKUP(B8,DishNotes!$B$2:$E$573,4,FALSE)="!","!","") -> ! | F8: Omelettes are enjoyed the world over! In Japan eggs are mixed with soy sauce, rice vinegar and sugar to give the starting base to the omelette. | G8: Omeletter bliver nydt i hele verden! I Japan blandes æg med soya, riseddike og sukker for at skabe basen til omeletten. | H8: Omelettes sind eine beliebte Eierspeise. In Japan werden die Eier mit Sojasauce, Reisessig und Zucker vermischt, um die Basis dieses Gerichts zu bilden.
A9: Japanese Pasta | B9: 930 | D9: =VLOOKUP(B9,[1]ManipulationPage!$A$3:$D$541,4,FALSE) -> Asia | E9: =IF(VLOOKUP(B9,DishNotes!$B$2:$E$573,4,FALSE)="!","!","") -> !
A10: Kimchi Sandwich | B10: 552 | D10: =VLOOKUP(B10,[1]ManipulationPage!$A$3:$D$541,4,FALSE) -> Asia | E10: =IF(VLOOKUP(B10,DishNotes!$B$2:$E$573,4,FALSE)="!","!","")
A11: Korean Kimchi Stew | B11: 1012 | C11: 5855 | D11: =VLOOKUP(B11,[1]ManipulationPage!$A$3:$D$541,4,FALSE) -> Asia | E11: =IF(VLOOKUP(B11,DishNotes!$B$2:$E$573,4,FALSE)="!","!","")
A12: Korean Pasta | B12: 931 | D12: =VLOOKUP(B12,[1]ManipulationPage!$A$3:$D$541,4,FALSE) -> Asia | E12: =IF(VLOOKUP(B12,DishNotes!$B$2:$E$573,4,FALSE)="!","!","") -> !
A13: Korean Style Pizza | B13: 61 | C13: 1288 | D13: =VLOOKUP(B13,[1]ManipulationPage!$A$3:$D$541,4,FALSE) -> Asia | E13: =IF(VLOOKUP(B13,DishNotes!$B$2:$E$573,4,FALSE)="!","!","") -> ! | F13: Give the classical pizza a twist with a Korean inspired base of soy sauce, brown sugar and sesame oil! | G13: Giv denne klassiske pizza et twist af koreansk inspireret base af sojasovs, brun sukker og sesam olie! | H13: Verleihe klassischer Pizza einen besonderen Geschmack mit koreanisch inspirierten Aromen.
A14: Miso Soup | B14: 56 | C14: 1258 | D14: =VLOOKUP(B14,[1]ManipulationPage!$A$3:$D$541,4,FALSE) -> Asia | E14: =IF(VLOOKUP(B14,DishNotes!$B$2:$E$573,4,FALSE)="!","!","") -> ! | F14: Miso soup is a traditional Japanese soup that lies at the heart of Japanese cuisine. Miso paste, a fermented soybean paste, creates the base of this soup. | G14: Miso suppe er en traditionel japansk suppe og udgør hjertet af det japansk køkken. Det er miso pasta, en fermenteret sojabønnepasta, der skaber basen af denne lækre suppe. | H14: Miso Suppe ist ein Klassiker der japanischen Küche. Miso Paste, eine fermentierte Sojabohnenpaste, bildet die Basis dieser Suppe.
A15: Pad Thai | B15: 258 | C15: 2421 | D15: =VLOOKUP(B15,[1]ManipulationPage!$A$3:$D$541,4,FALSE) -> Asia | E15: =IF(VLOOKUP(B15,DishNotes!$B$2:$E$573,4,FALSE)="!","!","") -> ! | F15: Create your very own take on this traditional national Thai dish. Let out AI help pair your ingredients together! | G15: Create your very own take on this traditional national Thai dish. Let out AI help pair your ingredients together! | H15: Kreiere deine eigene Version dieses traditionellen Thai-Gerichts. Die KI hilft dir, passende Zutaten zu finden!
A16: Ramen | B16: 1059 | C16: 7732 | D16: =VLOOKUP(B16,[1]ManipulationPage!$A$3:$D$541,4,FALSE) -> Asia | E16: =IF(VLOOKUP(B16,DishNotes!$B$2:$E$573,4,FALSE)="!","!","") -> !
A17: Sichuan Roasted Veggies | B17: 317 | C17: 2713 | D17: =VLOOKUP(B17,[1]ManipulationPage!$A$3:$D$541,4,FALSE) -> Asia | E17: =IF(VLOOKUP(B17,DishNotes!$B$2:$E$573,4,FALSE)="!","!","") -> ! | F17: A delicious oven-roasted veggie dish inspired by ingredients from the Sichuan region of China. | G17: A delicious oven-roasted veggie dish inspired by ingredients from the Sichuan region of China. | H17: A delicious oven-roasted veggie dish inspired by ingredients from the Sichuan region of China.
A18: Sichuan Stir-Fry | B18: 967 | C18: 5059 | D18: =VLOOKUP(B18,[1]ManipulationPage!$A$3:$D$541,4,FALSE) -> Asia | E18: =IF(VLOOKUP(B18,DishNotes!$B$2:$E$573,4,FALSE)="!","!","") -> !
A19: Tofu Stir-Fry | B19: 969 | C19: 5087 | D19: =VLOOKUP(B19,[1]ManipulationPage!$A$3:$D$541,4,FALSE) -> Asia | E19: =IF(VLOOKUP(B19,DishNotes!$B$2:$E$573,4,FALSE)="!","!","") -> !
A20: Banana Protein Bites | B20: 389 | C20: 2927 | D20: =VLOOKUP(B20,[1]ManipulationPage!$A$3:$D$541,4,FALSE) -> Baking | E20: =IF(VLOOKUP(B20,DishNotes!$B$2:$E$573,4,FALSE)="!","!","") | F20: Energy balls are a tasty and healthy homemade snack. Keep them in your fridge for a quick bite. | G20: Energikuglerne er en lækker og sund hjemmelavet snack. Bevar dem i dit køleskab til når du er lidt lækkersulten. | H20: Energy balls are a tasty and healthy homemade snack. Keep them in your fridge for a quick bite.
A21: Banana slices | B21: 777 | C21: 3725 | D21: =VLOOKUP(B21,[1]ManipulationPage!$A$3:$D$541,4,FALSE) -> Baking | E21: =IF(VLOOKUP(B21,DishNotes!$B$2:$E$573,4,FALSE)="!","!","")
A22: Beetroot Choco Cake | B22: 447 | C22: 3065 | D22: =VLOOKUP(B22,[1]ManipulationPage!$A$3:$D$541,4,FALSE) -> Baking | E22: =IF(VLOOKUP(B22,DishNotes!$B$2:$E$573,4,FALSE)="!","!","") | F22: The earthy taste of beetroot goes perfectly with chocolate. | G22: Den jordiske smag af rødbeder passer perfekt med chokolade. | H22: The earthy taste of beetroot goes perfectly with chocolate.
A23: Berry Almond Brownie | B23: 627 | C23: 3388 | D23: =VLOOKUP(B23,[1]ManipulationPage!$A$3:$D$541,4,FALSE) -> Baking | E23: =IF(VLOOKUP(B23,DishNotes!$B$2:$E$573,4,FALSE)="!","!","") | F23: This is an upgrade for brownies — try it out yourself! It can also be a great gift for a dear friend.
A24: Berry Almond Brownies | B24: 628 | C24: 3390 | D24: =VLOOKUP(B24,[1]ManipulationPage!$A$3:$D$541,4,FALSE) -> Baking | E24: =IF(VLOOKUP(B24,DishNotes!$B$2:$E$573,4,FALSE)="!","!","") | F24: This is an upgrade for brownies — try it out yourself! It can also be a great gift for a dear friend.
A25: Berry Muffins | B25: 467 | C25: 3099 | D25: =VLOOKUP(B25,[1]ManipulationPage!$A$3:$D$541,4,FALSE) -> Baking | E25: =IF(VLOOKUP(B25,DishNotes!$B$2:$E$573,4,FALSE)="!","!","") | F25: Berries are wonderful in desserts. The balance of sweet, sour and fresh is perfect for baking. | G25: Bær er vidunderlige i desserter. Den søde, syrlige og friske kombination er perfekt til bagning. | H25: Beeren wirken Wunder in Nachspeisen. Die süß-saure und frische Symphonie eignet sich perfekt zum Backen.
A26: Black Bean Brownies | B26: 457 | C26: 3080 | D26: =VLOOKUP(B26,[1]ManipulationPage!$A$3:$D$541,4,FALSE) -> Baking | E26: =IF(VLOOKUP(B26,DishNotes!$B$2:$E$573,4,FALSE)="!","!","") | F26: These chocolatey treats are made with healthy ingredients. | G26: Disse chokolade indholdige godbidder er lavet med sunde ingredienser. | H26: These chocolatey treats are made with healthy ingredients.
A27: Bread Buns | B27: 1149 | C27: 10080 | D27: =VLOOKUP(B27,[1]ManipulationPage!$A$3:$D$541,4,FALSE) -> Baking | E27: =IF(VLOOKUP(B27,DishNotes!$B$2:$E$573,4,FALSE)="!","!","")
A28: Bread Pudding Dessert | B28: 421 | C28: 3011 | D28: =VLOOKUP(B28,[1]ManipulationPage!$A$3:$D$541,4,FALSE) -> Baking | E28: =IF(VLOOKUP(B28,DishNotes!$B$2:$E$573,4,FALSE)="!","!","") | F28: This recipe transforms leftover stale bread into a sweet treat.
A29: Breakfast Buns | B29: 481 | C29: 3125 | D29: =VLOOKUP(B29,[1]ManipulationPage!$A$3:$D$541,4,FALSE) -> Baking | E29: =IF(VLOOKUP(B29,DishNotes!$B$2:$E$573,4,FALSE)="!","!","") | F29: Get creative with mixing in nuts, seeds, spices, or dried fruit! | G29: Vær kreativ ved at blande nødder, frø, krydderier eller tørret frugt i bollerne! | H29: Get creative with mixing in nuts, seeds, spices, or dried fruit!
A30: Buchteln | B30: 743 | C30: 3657 | D30: =VLOOKUP(B30,[1]ManipulationPage!$A$3:$D$541,4,FALSE) -> Baking | E30: =IF(VLOOKUP(B30,DishNotes!$B$2:$E$573,4,FALSE)="!","!","")
A31: Bundt Cake | B31: 1153 | C31: 10096 | D31: =VLOOKUP(B31,[1]ManipulationPage!$A$3:$D$541,4,FALSE) -> Baking | E31: =IF(VLOOKUP(B31,DishNotes!$B$2:$E$573,4,FALSE)="!","!","")
A32: Chia Pudding | B32: 667 | C32: 3486 | D32: =VLOOKUP(B32,[1]ManipulationPage!$A$3:$D$541,4,FALSE) -> Baking | E32: =IF(VLOOKUP(B32,DishNotes!$B$2:$E$573,4,FALSE)="!","!","") | F32: Enjoy a healthy and nutritious chia based porridge for a great quick start to the morning. | G32: Nyd en sund og nærende chia-baseret grød til en god hurtig start på dagen. | H32: Genieße einen gesunden und nahrhaften Brei auf Chia-Basis für einen guten Start in den Morgen.
A33: Choco Berry Muffins | B33: 826 | C33: 3829 | D33: =VLOOKUP(B33,[1]ManipulationPage!$A$3:$D$541,4,FALSE) -> Baking | E33: =IF(VLOOKUP(B33,DishNotes!$B$2:$E$573,4,FALSE)="!","!","") | F33: Feel like dessert? Create a classic muffin. | G33: Lyst til dessert? Lav en klassisk muffin. | H33: Lust auf Dessert? Machen Sie einen klassischen Muffin.
A34: Chocolate Brownie | B34: 600 | C34: 3294 | D34: =VLOOKUP(B34,[1]ManipulationPage!$A$3:$D$541,4,FALSE) -> Baking | E34: =IF(VLOOKUP(B34,DishNotes!$B$2:$E$573,4,FALSE)="!","!","") | F34: Chocolate Brownie with Agrain 03 Maskmel Stout
A35: Chocolate Chip Banana Bread | B35: 429 | C35: 3036 | D35: =VLOOKUP(B35,[1]ManipulationPage!$A$3:$D$541,4,FALSE) -> Baking | E35: =IF(VLOOKUP(B35,DishNotes!$B$2:$E$573,4,FALSE)="!","!","") | F35: Are your bananas turning brown? Then they are perfect for this delicious recipe. | G35: Bliver dine bananer brune? Så er de perfekte til denne lækre opskrift. | H35: Are your bananas turning brown? Then they are perfect for this delicious recipe.
A36: Chocolate Mousse | B36: 687 | C36: 3533 | D36: =VLOOKUP(B36,[1]ManipulationPage!$A$3:$D$541,4,FALSE) -> Baking | E36: =IF(VLOOKUP(B36,DishNotes!$B$2:$E$573,4,FALSE)="!","!","") | F36: Chill the mousse for at least 2 hours, but the longer you wait the tastier!
A37: Cinnamon Swirls | B37: 477 | C37: 3117 | D37: =VLOOKUP(B37,[1]ManipulationPage!$A$3:$D$541,4,FALSE) -> Baking | E37: =IF(VLOOKUP(B37,DishNotes!$B$2:$E$573,4,FALSE)="!","!","") | F37: If you have your homemade Dough Base, skip straight to the filling and baking! | G37: Hvis du har din hjemmelavede dejbase, skal du springe direkte til fyldet og bagning! | H37: If you have your homemade Dough Base, skip straight to the filling and baking!
A38: Classic bundt cake | B38: 676 | C38: 3510 | D38: =VLOOKUP(B38,[1]ManipulationPage!$A$3:$D$541,4,FALSE) -> Baking | E38: =IF(VLOOKUP(B38,DishNotes!$B$2:$E$573,4,FALSE)="!","!","")
A39: Classic bundt cake | B39: 685 | C39: 3528 | D39: =VLOOKUP(B39,[1]ManipulationPage!$A$3:$D$541,4,FALSE) -> Baking | E39: =IF(VLOOKUP(B39,DishNotes!$B$2:$E$573,4,FALSE)="!","!","")
A40: Classic Cheesecake | B40: 391 | C40: 2936 | D40: =VLOOKUP(B40,[1]ManipulationPage!$A$3:$D$541,4,FALSE) -> Baking | E40: =IF(VLOOKUP(B40,DishNotes!$B$2:$E$573,4,FALSE)="!","!","") | F40: A traditional cheesecake recipe - creamy, smooth, and dreamy... | G40: En traditionel cheesecake opskrift - cremet, glat og helt drømmende ... | H40: A traditional cheesecake recipe - creamy, smooth, and dreamy...
A41: Cocoa Muffins | B41: 375 | C41: 2892 | D41: =VLOOKUP(B41,[1]ManipulationPage!$A$3:$D$541,4,FALSE) -> Baking | E41: =IF(VLOOKUP(B41,DishNotes!$B$2:$E$573,4,FALSE)="!","!","") | F41: Feel like dessert? Create a classic muffin. | G41: Lyst til dessert? Lav en klassisk muffin. | H41: Lust auf Dessert? Machen Sie einen klassischen Muffin.
A42: Coconut Muesli Bar | B42: 433 | C42: 3044 | D42: =VLOOKUP(B42,[1]ManipulationPage!$A$3:$D$541,4,FALSE) -> Baking | E42: =IF(VLOOKUP(B42,DishNotes!$B$2:$E$573,4,FALSE)="!","!","") | F42: Muesli bars are convenient and tasty on the go. | G42: Müslibarer er praktisk og velsmagende på farten. | H42: Muesli bars are convenient and tasty on the go.
A43: Coconut Pecan Granola | B43: 407 | C43: 2979 | D43: =VLOOKUP(B43,[1]ManipulationPage!$A$3:$D$541,4,FALSE) -> Baking | E43: =IF(VLOOKUP(B43,DishNotes!$B$2:$E$573,4,FALSE)="!","!","") | F43: Homemade granola is a crunchy and delicious choice for breakfast, a snack, or topping. | G43: Homemade granola is a crunchy and delicious choice for breakfast, a snack, or topping. | H43: Homemade granola is a crunchy and delicious choice for breakfast, a snack, or topping.
A44: Covered apple pie | B44: 673 | C44: 3504 | D44: =VLOOKUP(B44,[1]ManipulationPage!$A$3:$D$541,4,FALSE) -> Baking | E44: =IF(VLOOKUP(B44,DishNotes!$B$2:$E$573,4,FALSE)="!","!","")
A45: Covered apple pie | B45: 684 | C45: 3526 | D45: =VLOOKUP(B45,[1]ManipulationPage!$A$3:$D$541,4,FALSE) -> Baking | E45: =IF(VLOOKUP(B45,DishNotes!$B$2:$E$573,4,FALSE)="!","!","")
A46: Cranberry Almond Granola Bar | B46: 431 | C46: 3042 | D46: =VLOOKUP(B46,[1]ManipulationPage!$A$3:$D$541,4,FALSE) -> Baking | E46: =IF(VLOOKUP(B46,DishNotes!$B$2:$E$573,4,FALSE)="!","!","") | F46: Muesli bars are convenient and tasty on the go. | G46: Müslibarer er praktisk og velsmagende på farten. | H46: Muesli bars are convenient and tasty on the go.
A47: Creamy Baileys Mascarpone Dip | B47: 695 | C47: 3554 | D47: =VLOOKUP(B47,[1]ManipulationPage!$A$3:$D$541,4,FALSE) -> Baking | E47: =IF(VLOOKUP(B47,DishNotes!$B$2:$E$573,4,FALSE)="!","!","") | F47: Dip your favorite cookies and fruits into this creamy deliciousness!
A48: Dark Romance Infused Pancakes | B48: 658 | C48: 3468 | D48: =VLOOKUP(B48,[1]ManipulationPage!$A$3:$D$541,4,FALSE) -> Baking | E48: =IF(VLOOKUP(B48,DishNotes!$B$2:$E$573,4,FALSE)="!","!","")
A49: Espresso Chocolate Cake | B49: 453 | C49: 3073 | D49: =VLOOKUP(B49,[1]ManipulationPage!$A$3:$D$541,4,FALSE) -> Baking | E49: =IF(VLOOKUP(B49,DishNotes!$B$2:$E$573,4,FALSE)="!","!","") | F49: Coffee enhances the chocolate in this deep and darkly flavored cake. | G49: Kaffe forbedrer chokoladen i denne dybe og mørke smagfulde kage. | H49: Coffee enhances the chocolate in this deep and darkly flavored cake.
A50: French Toast | B50: 1157 | C50: 10276 | D50: =VLOOKUP(B50,[1]ManipulationPage!$A$3:$D$541,4,FALSE) -> Baking | E50: =IF(VLOOKUP(B50,DishNotes!$B$2:$E$573,4,FALSE)="!","!","") | F50: This recipe transforms leftover stale bread into a sweet treat.
A51: Fruit & Cream Cake | B51: 417 | C51: 3004 | D51: =VLOOKUP(B51,[1]ManipulationPage!$A$3:$D$541,4,FALSE) -> Baking | E51: =IF(VLOOKUP(B51,DishNotes!$B$2:$E$573,4,FALSE)="!","!","") | F51: This cake is sure to impress with lots of juicy fruits to complement the pillowy whipped cream topping. | G51: Denne kage skal nok imponere, med masser af saftig frugt oven på blød og luftigt flødeskum. | H51: This cake is sure to impress with lots of juicy fruits to complement the pillowy whipped cream topping.
A52: Gingerbread cookies | B52: 621 | C52: 3384 | D52: =VLOOKUP(B52,[1]ManipulationPage!$A$3:$D$541,4,FALSE) -> Baking | E52: =IF(VLOOKUP(B52,DishNotes!$B$2:$E$573,4,FALSE)="!","!","") | F52: Today is a great time for aromatic gingerbread cookies! Enjoy the process and the taste of this delicious treat.
A53: Gluten Free Bread | B53: 1148 | C53: 10078 | D53: =VLOOKUP(B53,[1]ManipulationPage!$A$3:$D$541,4,FALSE) -> Baking | E53: =IF(VLOOKUP(B53,DishNotes!$B$2:$E$573,4,FALSE)="!","!","") | F53: Nothing compares to the smell of homemade bread baking in the oven... And the taste is even better. | G53: Intet kan sammenlignes med duften af ​​hjemmelavet brød der bager i ovnen ... Og smagen er endnu bedre. | H53: Nothing compares to the smell of homemade bread baking in the oven... And the taste is even better.
A54: Gluten Free "Rye Bread" | B54: 517 | C54: 3193 | D54: =VLOOKUP(B54,[1]ManipulationPage!$A$3:$D$541,4,FALSE) -> Baking | E54: =IF(VLOOKUP(B54,DishNotes!$B$2:$E$573,4,FALSE)="!","!","") | F54: Inspired by traditional Danish rye bread, this gluten-free version is dense, soft and seedy.
A55: Gluten-Free Seed Crackers | B55: 419 | C55: 3008 | D55: =VLOOKUP(B55,[1]ManipulationPage!$A$3:$D$541,4,FALSE) -> Baking | E55: =IF(VLOOKUP(B55,DishNotes!$B$2:$E$573,4,FALSE)="!","!","") | F55: These seedy crackers are a healthy and savory snack, or the perfect crunchy accompaniment to a soup or salad. | G55: Dette sunde knækbrød er en sund og lækker snack, eller den perfekte sprøde akkompagnement til en suppe eller salat. | H55: These seedy crackers are a healthy and savory snack, or the perfect crunchy accompaniment to a soup or salad.
A56: Grandma's Carinthian cake | B56: 683 | C56: 3524 | D56: =VLOOKUP(B56,[1]ManipulationPage!$A$3:$D$541,4,FALSE) -> Baking | E56: =IF(VLOOKUP(B56,DishNotes!$B$2:$E$573,4,FALSE)="!","!","")
A57: Grandma's Carinthian cake | B57: 672 | C57: 3502 | D57: =VLOOKUP(B57,[1]ManipulationPage!$A$3:$D$541,4,FALSE) -> Baking | E57: =IF(VLOOKUP(B57,DishNotes!$B$2:$E$573,4,FALSE)="!","!","")
A58: Healthy Muffin | B58: 110 | C58: 1546 | D58: =VLOOKUP(B58,[1]ManipulationPage!$A$3:$D$541,4,FALSE) -> Baking | E58: =IF(VLOOKUP(B58,DishNotes!$B$2:$E$573,4,FALSE)="!","!","") | F58: Create a muffin without sugar, butter, ... | G58: Skab en muffin uden sukker, smør,... | H58: Kreiere ein Muffin ohne Zucker, Butter, ...
A59: Homemade Pizza Dough | B59: 245 | C59: 2343 | D59: =VLOOKUP(B59,[1]ManipulationPage!$A$3:$D$541,4,FALSE) -> Baking | E59: =IF(VLOOKUP(B59,DishNotes!$B$2:$E$573,4,FALSE)="!","!","") | F59: Create your own homemade pizza dough and add your favorite toppings to create a delicious pizza. | G59: Skab din egen hjemmelavet pizzadej og tilføj din ynglings topping for at skabe en lækker pizza. | H59: Create your own homemade pizza dough and add your favorite toppings to create a delicious pizza.
A60: Jalapeño Corn Muffins | B60: 367 | C60: 2871 | D60: =VLOOKUP(B60,[1]ManipulationPage!$A$3:$D$541,4,FALSE) -> Baking | E60: =IF(VLOOKUP(B60,DishNotes!$B$2:$E$573,4,FALSE)="!","!","") | F60: Make quick muffins for dinner! Containing about 50% veggies, they will be moist on the inside. | G60: Lav 30 minutters muffins til aftensmad! Grøntsagerne vil gøre dem lidt fugtige indeni, men tag ikke fejl - dejen er færdigbagt! | H60: Mache herzhafte Muffins zum Abendessen in nur 30 Minuten - mit ca. 50% Gemüse werden diese Muffins super saftig!
A61: Key Lime Pie | B61: 689 | C61: 3538 | D61: =VLOOKUP(B61,[1]ManipulationPage!$A$3:$D$541,4,FALSE) -> Baking | E61: =IF(VLOOKUP(B61,DishNotes!$B$2:$E$573,4,FALSE)="!","!","") | F61: If you have extra lime zest, use it as a garnish to make your pie beautiful!
A62: Layered cream cake | B62: 745 | C62: 3661 | D62: =VLOOKUP(B62,[1]ManipulationPage!$A$3:$D$541,4,FALSE) -> Baking | E62: =IF(VLOOKUP(B62,DishNotes!$B$2:$E$573,4,FALSE)="!","!","")
A63: Lemon Coconut Energy Balls | B63: 441 | C63: 3055 | D63: =VLOOKUP(B63,[1]ManipulationPage!$A$3:$D$541,4,FALSE) -> Baking | E63: =IF(VLOOKUP(B63,DishNotes!$B$2:$E$573,4,FALSE)="!","!","") | F63: Energy balls are a tasty and healthy homemade snack. Keep them in your fridge for a quick bite. | G63: Energikuglerne er en lækker og sund hjemmelavet snack. Bevar dem i dit køleskab til når du er lidt lækkersulten. | H63: Energy balls are a tasty and healthy homemade snack. Keep them in your fridge for a quick bite.
A64: Lemon poppy seed cake | B64: 718 | C64: 3605 | D64: =VLOOKUP(B64,[1]ManipulationPage!$A$3:$D$541,4,FALSE) -> Baking | E64: =IF(VLOOKUP(B64,DishNotes!$B$2:$E$573,4,FALSE)="!","!","")
A65: Muffins | B65: 813 | C65: 3801 | D65: =VLOOKUP(B65,[1]ManipulationPage!$A$3:$D$541,4,FALSE) -> Baking | E65: =IF(VLOOKUP(B65,DishNotes!$B$2:$E$573,4,FALSE)="!","!","") | F65: Feel like dessert? Create a classic muffin. | G65: Lyst til dessert? Lav en klassisk muffin. | H65: Lust auf Dessert? Machen Sie einen klassischen Muffin.
A66: Mushroom Toast | B66: 575 | C66: 3257 | D66: =VLOOKUP(B66,[1]ManipulationPage!$A$3:$D$541,4,FALSE) -> Baking | E66: =IF(VLOOKUP(B66,DishNotes!$B$2:$E$573,4,FALSE)="!","!","") | F66: Classic seasonal starter with a hint of natural saltiness from the sea
A67: New York Cheesecake | B67: 671 | C67: 3500 | D67: =VLOOKUP(B67,[1]ManipulationPage!$A$3:$D$541,4,FALSE) -> Baking | E67: =IF(VLOOKUP(B67,DishNotes!$B$2:$E$573,4,FALSE)="!","!","")
A68: New York Cheesecake | B68: 681 | C68: 3520 | D68: =VLOOKUP(B68,[1]ManipulationPage!$A$3:$D$541,4,FALSE) -> Baking | E68: =IF(VLOOKUP(B68,DishNotes!$B$2:$E$573,4,FALSE)="!","!","")
A69: No-bake Cheesecake | B69: 401 | C69: 2963 | D69: =VLOOKUP(B69,[1]ManipulationPage!$A$3:$D$541,4,FALSE) -> Baking | E69: =IF(VLOOKUP(B69,DishNotes!$B$2:$E$573,4,FALSE)="!","!","") | F69: Give your oven a day off with this recipe! | G69: Giv din ovn en fridag med denne opskrift! | H69: Give your oven a day off with this recipe!
A70: No Processed Sugar Muffins | B70: 373 | C70: 2888 | D70: =VLOOKUP(B70,[1]ManipulationPage!$A$3:$D$541,4,FALSE) -> Baking | E70: =IF(VLOOKUP(B70,DishNotes!$B$2:$E$573,4,FALSE)="!","!","") | F70: Create a muffin without processed sugar. | G70: Skab en muffin uden forarbejdet sukker | H70: Kreiere einen Muffin ohne Industrie-Zucker
A71: Nut Butter Cookies | B71: 397 | C71: 2950 | D71: =VLOOKUP(B71,[1]ManipulationPage!$A$3:$D$541,4,FALSE) -> Baking | E71: =IF(VLOOKUP(B71,DishNotes!$B$2:$E$573,4,FALSE)="!","!","") | F71: A classic sweet treat with a nutty twist. | G71: A classic sweet treat with a nutty twist. | H71: A classic sweet treat with a nutty twist.
A72: Nutty Chocolate Muffins | B72: 465 | C72: 3095 | D72: =VLOOKUP(B72,[1]ManipulationPage!$A$3:$D$541,4,FALSE) -> Baking | E72: =IF(VLOOKUP(B72,DishNotes!$B$2:$E$573,4,FALSE)="!","!","") | F72: Chocolate and nuts is a classical match in muffins. Sweet, bitter and crunchy! | G72: Chokolade og nødder er en klassisk kombination i muffins. Sød, bitter og knasende! | H72: Schokolade und Nüsse sind eine klassische Kombination für Muffins. Süß, bitter und knusprig!
A73: Oat Muffins | B73: 379 | C73: 2907 | D73: =VLOOKUP(B73,[1]ManipulationPage!$A$3:$D$541,4,FALSE) -> Baking | E73: =IF(VLOOKUP(B73,DishNotes!$B$2:$E$573,4,FALSE)="!","!","") | F73: These breakfast muffins with oats will be a perfect start to your day! | G73: Disse morgenmadsmuffins med havre vil være en perfekt start på din dag! | H73: Diese Frühstücksmuffins mit Hafer sind der perfekte Start in den Tag!
A74: Overnight Oats | B74: 73 | C74: 1366 | D74: =VLOOKUP(B74,[1]ManipulationPage!$A$3:$D$541,4,FALSE) -> Baking | E74: =IF(VLOOKUP(B74,DishNotes!$B$2:$E$573,4,FALSE)="!","!","") | F74: In a time crunch? Make some overnight oats so that your porridge breakfast is already waiting for you when you wake up! | G74: Travlt? Lav natten over havergrød - så er grød morgenmad klar til dig, når du står op! | H74: Morgens keine Zeit und Lust, dein Frühstück vorzubereiten? Overnight Oats sind die Lösung - ein richtiges Powerfrühstück!
A75: Overnight Oats with Hemp | B75: 907 | C75: 4024 | D75: =VLOOKUP(B75,[1]ManipulationPage!$A$3:$D$541,4,FALSE) -> Baking | E75: =IF(VLOOKUP(B75,DishNotes!$B$2:$E$573,4,FALSE)="!","!","") | F75: Lots of nutrient-rich fruits and healthy omega-3 fats in this filling and tasty breakfast. | G75: Masser af næringsrigt frugt og sunde omega-3 fedtsyre i denne lækker og mættende morgenmadsret.
A76: Peanut Butter Bars | B76: 435 | C76: 3048 | D76: =VLOOKUP(B76,[1]ManipulationPage!$A$3:$D$541,4,FALSE) -> Baking | E76: =IF(VLOOKUP(B76,DishNotes!$B$2:$E$573,4,FALSE)="!","!","") | F76: Muesli bars are convenient and tasty on the go. | G76: Müslibarer er praktisk og velsmagende på farten. | H76: Muesli bars are convenient and tasty on the go.
A77: Pesto Garlic Swirls | B77: 479 | C77: 3121 | D77: =VLOOKUP(B77,[1]ManipulationPage!$A$3:$D$541,4,FALSE) -> Baking | E77: =IF(VLOOKUP(B77,DishNotes!$B$2:$E$573,4,FALSE)="!","!","") | F77: Use your homemade Dough Base to build a pizza for a tasty dinner idea. | G77: Brug din hjemmelavet Dej til at bygge basen til en lækker pizza. | H77: Use your homemade Dough Base to build a pizza for a tasty dinner idea.
A78: Pumpkin Nut Cake | B78: 449 | C78: 3067 | D78: =VLOOKUP(B78,[1]ManipulationPage!$A$3:$D$541,4,FALSE) -> Baking | E78: =IF(VLOOKUP(B78,DishNotes!$B$2:$E$573,4,FALSE)="!","!","") | F78: Warming spices and pumpkin are perfect for fall. | G78: Varmende krydderier og græskar er perfekte til efteråret. | H78: Warming spices and pumpkin are perfect for fall.
A79: Quick Soda Bread | B79: 511 | C79: 3181 | D79: =VLOOKUP(B79,[1]ManipulationPage!$A$3:$D$541,4,FALSE) -> Baking | E79: =IF(VLOOKUP(B79,DishNotes!$B$2:$E$573,4,FALSE)="!","!","") | F79: Quick breads are made without yeast or sourdough, and uses baking powder for the leavening. It's the perfect recipe for making bread in a hurry – no time spent kneading or rising. | G79: Quick breads are made without yeast or sourdough, and uses baking powder for the leavening. It's the perfect recipe for making bread in a hurry – no time spent kneading or rising. | H79: Quick breads are made without yeast or sourdough, and uses baking powder for the leavening. It's the perfect recipe for making bread in a hurry – no time spent kneading or rising.
A80: Red Velvet Cake | B80: 713 | C80: 3597 | D80: =VLOOKUP(B80,[1]ManipulationPage!$A$3:$D$541,4,FALSE) -> Baking | E80: =IF(VLOOKUP(B80,DishNotes!$B$2:$E$573,4,FALSE)="!","!","") | F80: This classic cake is unbelievably moist, fluffy, flavorful, and perfectly red.
A81: Rhubarb and mango jam | B81: 1023 | C81: 6297 | D81: =VLOOKUP(B81,[1]ManipulationPage!$A$3:$D$541,4,FALSE) -> Baking | E81: =IF(VLOOKUP(B81,DishNotes!$B$2:$E$573,4,FALSE)="!","!","")
A82: Rhubarb Cake | B82: 413 | C82: 2994 | D82: =VLOOKUP(B82,[1]ManipulationPage!$A$3:$D$541,4,FALSE) -> Baking | E82: =IF(VLOOKUP(B82,DishNotes!$B$2:$E$573,4,FALSE)="!","!","") | F82: Choose fruits that are in season for the best flavor experience. | G82: Vælg frugt i sæson for den bedste smagsoplevelse. | H82: Choose fruits that are in season for the best flavor experience.
A83: Rhubarb curd | B83: 1028 | C83: 6307 | D83: =VLOOKUP(B83,[1]ManipulationPage!$A$3:$D$541,4,FALSE) -> Baking | E83: =IF(VLOOKUP(B83,DishNotes!$B$2:$E$573,4,FALSE)="!","!","")
A84: Rhubarb jelly with elderflower | B84: 1027 | C84: 6305 | D84: =VLOOKUP(B84,[1]ManipulationPage!$A$3:$D$541,4,FALSE) -> Baking | E84: =IF(VLOOKUP(B84,DishNotes!$B$2:$E$573,4,FALSE)="!","!","")
A85: Rhubarb syrup | B85: 871 | C85: 3927 | D85: =VLOOKUP(B85,[1]ManipulationPage!$A$3:$D$541,4,FALSE) -> Baking | E85: =IF(VLOOKUP(B85,DishNotes!$B$2:$E$573,4,FALSE)="!","!","")
A86: Rice Pudding | B86: 711 | C86: 3587 | D86: =VLOOKUP(B86,[1]ManipulationPage!$A$3:$D$541,4,FALSE) -> Baking | E86: =IF(VLOOKUP(B86,DishNotes!$B$2:$E$573,4,FALSE)="!","!","") | F86: Use short grain white rice for the creamiest results.
A87: Root Vegetable Muffins | B87: 38 | C87: 1180 | D87: =VLOOKUP(B87,[1]ManipulationPage!$A$3:$D$541,4,FALSE) -> Baking | E87: =IF(VLOOKUP(B87,DishNotes!$B$2:$E$573,4,FALSE)="!","!","") | F87: Yes - you can eat muffins for dinner! Not the sweet kind, but savory muffins with veggies inside | G87: Ja, du kan spise muffins til aftensmad! Ikke den søde slags, men umami med grøntsager indeni! | H87: Ja - du kannst Muffins zum Abendbrot essen! Zwar keine Süßen, aber herzhafte Muffins mit Gemüse.
A88: Rye Bread | B88: 579 | C88: 3261 | D88: =VLOOKUP(B88,[1]ManipulationPage!$A$3:$D$541,4,FALSE) -> Baking | E88: =IF(VLOOKUP(B88,DishNotes!$B$2:$E$573,4,FALSE)="!","!","") | F88: The easy rye bread without sourdough with Agrain® 03 Stout Super Grain Flour
A89: Rye Bread | B89: 515 | C89: 3189 | D89: =VLOOKUP(B89,[1]ManipulationPage!$A$3:$D$541,4,FALSE) -> Baking | E89: =IF(VLOOKUP(B89,DishNotes!$B$2:$E$573,4,FALSE)="!","!","") | F89: Ask a friend or your local bakery for some sourdough starter, or learn to make your own! | G89: Ask a friend or your local bakery for some sourdough starter, or learn to make your own! | H89: Ask a friend or your local bakery for some sourdough starter, or learn to make your own!
A90: Rye Sesame Seed Crackers | B90: 409 | C90: 2987 | D90: =VLOOKUP(B90,[1]ManipulationPage!$A$3:$D$541,4,FALSE) -> Baking | E90: =IF(VLOOKUP(B90,DishNotes!$B$2:$E$573,4,FALSE)="!","!","") | F90: These seedy crackers are a healthy and savory snack, or the perfect crunchy accompaniment to a soup or salad. | G90: Dette sunde knækbrød er en sund og lækker snack, eller den perfekte sprøde akkompagnement til en suppe eller salat. | H90: These seedy crackers are a healthy and savory snack, or the perfect crunchy accompaniment to a soup or salad.
A91: Savory Bread Pudding | B91: 423 | C91: 3017 | D91: =VLOOKUP(B91,[1]ManipulationPage!$A$3:$D$541,4,FALSE) -> Baking | E91: =IF(VLOOKUP(B91,DishNotes!$B$2:$E$573,4,FALSE)="!","!","") | F91: This recipe will give new life to stale bread!
A92: Savory Zucchini Muffins | B92: 497 | C92: 3143 | D92: =VLOOKUP(B92,[1]ManipulationPage!$A$3:$D$541,4,FALSE) -> Baking | E92: =IF(VLOOKUP(B92,DishNotes!$B$2:$E$573,4,FALSE)="!","!","") | F92: Make quick muffins for dinner! Containing about 50% veggies, they will be moist on the inside. | G92: Lav 30 minutters muffins til aftensmad! Grøntsagerne vil gøre dem lidt fugtige indeni, men tag ikke fejl - dejen er færdigbagt! | H92: Mache herzhafte Muffins zum Abendessen in nur 30 Minuten - mit ca. 50% Gemüse werden diese Muffins super saftig!
A93: Scones | B93: 425 | C93: 3025 | D93: =VLOOKUP(B93,[1]ManipulationPage!$A$3:$D$541,4,FALSE) -> Baking | E93: =IF(VLOOKUP(B93,DishNotes!$B$2:$E$573,4,FALSE)="!","!","") | F93: A buttery and soft treat to go with your coffee or tea. | G93: En smøragtig og blød godbid til at gå med din kaffe eller te. | H93: A buttery and soft treat to go with your coffee or tea.
A94: Sesame Snaps | B94: 712 | C94: 3590 | D94: =VLOOKUP(B94,[1]ManipulationPage!$A$3:$D$541,4,FALSE) -> Baking | E94: =IF(VLOOKUP(B94,DishNotes!$B$2:$E$573,4,FALSE)="!","!","") | F94: The thinner you roll out the Sesame Snaps, the crunchier they get!
A95: Simple Paleo Cupcake | B95: 574 | C95: 3255 | D95: =VLOOKUP(B95,[1]ManipulationPage!$A$3:$D$541,4,FALSE) -> Baking | E95: =IF(VLOOKUP(B95,DishNotes!$B$2:$E$573,4,FALSE)="!","!","") | F95: Recipe developed by Jenny Tschiesche BSc(Hons) Dip(ION) FdSc BANT. For more information see www.jennytschiesche.com.
A96: Snowball coconut bites | B96: 625 | C96: 3386 | D96: =VLOOKUP(B96,[1]ManipulationPage!$A$3:$D$541,4,FALSE) -> Baking | E96: =IF(VLOOKUP(B96,DishNotes!$B$2:$E$573,4,FALSE)="!","!","") | F96: In just a few minutes you can make a delicious treat to share with your closest ones.
A97: sourdough bread | B97: 385 | C97: 2917 | D97: =VLOOKUP(B97,[1]ManipulationPage!$A$3:$D$541,4,FALSE) -> Baking | E97: =IF(VLOOKUP(B97,DishNotes!$B$2:$E$573,4,FALSE)="!","!","") | F97: You'll need a sourdough starter for this bread, which will help it to rise, and give it a tangy flavor. | G97: Du skal bruge surdej til dette brød, som vil hjælpe det til at hæve, og give det en krydret smag. | H97: You'll need a sourdough starter for this bread, which will help it to rise, and give it a tangy flavor.
A98: Sourdough Rye Bread | B98: 509 | C98: 3177 | D98: =VLOOKUP(B98,[1]ManipulationPage!$A$3:$D$541,4,FALSE) -> Baking | E98: =IF(VLOOKUP(B98,DishNotes!$B$2:$E$573,4,FALSE)="!","!","") | F98: Ask a friend or your local bakery for some sourdough starter, or learn to make your own! | G98: Ask a friend or your local bakery for some sourdough starter, or learn to make your own! | H98: Ask a friend or your local bakery for some sourdough starter, or learn to make your own!
A99: Strawberry Traybake Cake | B99: 677 | C99: 3512 | D99: =VLOOKUP(B99,[1]ManipulationPage!$A$3:$D$541,4,FALSE) -> Baking | E99: =IF(VLOOKUP(B99,DishNotes!$B$2:$E$573,4,FALSE)="!","!","")
A100: Vegan Apple Cake | B100: 415 | C100: 2999 | D100: =VLOOKUP(B100,[1]ManipulationPage!$A$3:$D$541,4,FALSE) -> Baking | E100: =IF(VLOOKUP(B100,DishNotes!$B$2:$E$573,4,FALSE)="!","!","") | F100: Use this basic cake recipe as the foundation for a tasty dessert. | G100: Brug denne grundlæggende kage opskrift som grundlaget for en velsmagende dessert. | H100: Use this basic cake recipe as the foundation for a tasty dessert.
...
